{"code":"0","data":{"list":[{"baId":"1593053315510333442","projectCode":"2211-441900-04-01-844807","totalMoney":50.0000,"fullName":"东莞市发展和改革局","finishDate":"2022-11-17","stateFlagName":"办结（通过）","projectName":"光烨园洲桥公交枢纽充电站升级项目"},{"baId":"1593074636449411073","projectCode":"2211-441900-04-01-753542","totalMoney":112.8000,"fullName":"东莞市桥头镇经济发展局","finishDate":"2022-11-17","stateFlagName":"办结（通过）","projectName":"聚能光伏(深圳)有限公司李汉钦250.38KW光伏发电项目"},{"baId":"1593076458689949698","projectCode":"2211-441900-04-01-185998","totalMoney":100.0000,"fullName":"东莞市常平镇经济发展局","finishDate":"2022-11-17","stateFlagName":"办结（通过）","projectName":"东莞市吉瀛科技有限公司99.35kW分布式光伏发电项目"},{"baId":"1593085760838332418","projectCode":"2211-441900-04-01-698004","totalMoney":51900.0000,"fullName":"东莞市东城街道经济发展局","finishDate":"2022-11-17","stateFlagName":"办结（通过）","projectName":"中能建投东城同沙101.9MW分布式光伏项目"},{"baId":"1593085793742647297","projectCode":"2211-441900-04-01-772163","totalMoney":31900.0000,"fullName":"东莞市东城街道经济发展局","finishDate":"2022-11-17","stateFlagName":"办结（通过）","projectName":"中能建投东城牛山62.65MW分布式光伏项目"},{"baId":"1593085826571464706","projectCode":"2211-441900-04-01-156526","totalMoney":23000.0000,"fullName":"东莞市东城街道经济发展局","finishDate":"2022-11-17","stateFlagName":"办结（通过）","projectName":"中能建投东城温塘45.18MW分布式光伏项目"},{"baId":"1593085851598876674","projectCode":"2211-441900-04-01-202777","totalMoney":16800.0000,"fullName":"东莞市东城街道经济发展局","finishDate":"2022-11-17","stateFlagName":"办结（通过）","projectName":"中能建投东城桑园33.04MW分布式光伏项目"},{"baId":"1593091246505619458","projectCode":"2211-441900-04-05-949983","totalMoney":103.4600,"fullName":"东莞市凤岗镇经济发展局","finishDate":"2022-11-17","stateFlagName":"办结（通过）","projectName":"东莞市永益产业园运营有限公司246.34Kw分布式光伏发电项目"},{"baId":"1593091284828975106","projectCode":"2211-441900-04-01-386660","totalMoney":5256.5000,"fullName":"东莞市凤岗镇经济发展局","finishDate":"2022-11-17","stateFlagName":"办结（通过）","projectName":" 东莞市净诺环境科技股份有限公司工业厂区"},{"baId":"1593093871766630401","projectCode":"2204-441900-04-01-737407","totalMoney":30000.0000,"fullName":"东莞市松山湖产业发展局","finishDate":"2022-11-17","stateFlagName":"办结（通过）","projectName":"生态园南城智科园"},{"baId":"1593106657569697793","projectCode":"2211-441900-04-01-491351","totalMoney":125.0000,"fullName":"东莞市大岭山镇经济发展局","finishDate":"2022-11-17","stateFlagName":"办结（通过）","projectName":"中科储恒250.8KWp分布式光伏发电项目"},{"baId":"1593167055459217409","projectCode":"2211-441900-04-01-854407","totalMoney":125.0000,"fullName":"东莞市大岭山镇经济发展局","finishDate":"2022-11-17","stateFlagName":"办结（通过）","projectName":"东莞市乐能智慧电力技术服务有限公司（五千年红木）290.4kWp分布式光伏发电项目"},{"baId":"1592683871722303490","projectCode":"2211-441900-04-01-138397","totalMoney":141.5800,"fullName":"东莞市大岭山镇经济发展局","finishDate":"2022-11-16","stateFlagName":"办结（通过）","projectName":"东莞冠威绿之宝实业有限公司153.69kWp分布式光伏发电项目"},{"baId":"1592714070543331330","projectCode":"2211-441900-04-01-728132","totalMoney":28.0000,"fullName":"东莞市石排镇经济发展局","finishDate":"2022-11-16","stateFlagName":"办结（通过）","projectName":"东莞市弘景新能源集团有限公司84.24KW分布式光伏发电项目"},{"baId":"1592714071260557314","projectCode":"2211-441900-04-01-801294","totalMoney":76.0000,"fullName":"东莞市石排镇经济发展局","finishDate":"2022-11-16","stateFlagName":"办结（通过）","projectName":"东莞市弘景新能源集团有限公司283.5kw分布式光伏发电项目"}],"pageNumber":118,"pageSize":15,"totalPage":641,"totalRow":9605,"firstPage":false,"lastPage":false},"message":"查询成功！","status":200}