{"code":"0","data":{"list":[{"baId":"e17f294e-73ae-11ec-9ad9-fa164ee08b71","projectCode":"2020-441900-39-03-024689","totalMoney":75000.0000,"fullName":"东莞市松山湖产业发展局","finishDate":"2020-05-07","stateFlagName":"办结（通过）","projectName":"歌尔股份华南研发智慧园项目"},{"baId":"e19d769a-73ae-11ec-9ad9-fa164ee08b71","projectCode":"2020-441900-73-03-033419","totalMoney":80000.0000,"fullName":"东莞市松山湖产业发展局","finishDate":"2020-05-07","stateFlagName":"办结（通过）","projectName":"华润电力智慧能源研发中心项目"},{"baId":"e1a28bec-73ae-11ec-9ad9-fa164ee08b71","projectCode":"2020-441900-70-03-033968","totalMoney":220000.0000,"fullName":"东莞市麻涌镇经济发展局","finishDate":"2020-05-07","stateFlagName":"办结（通过）","projectName":"悦江花园"},{"baId":"e19d27b6-73ae-11ec-9ad9-fa164ee08b71","projectCode":"2020-441900-50-03-032161","totalMoney":235.0000,"fullName":"东莞市横沥镇经济发展局","finishDate":"2020-05-06","stateFlagName":"办结（通过）","projectName":"旧建筑立面改造"},{"baId":"e19e26a1-73ae-11ec-9ad9-fa164ee08b71","projectCode":"2020-441900-65-03-032988","totalMoney":35000.0000,"fullName":"东莞市松山湖产业发展局","finishDate":"2020-05-06","stateFlagName":"办结（通过）","projectName":"金蝶互联网业务中心"},{"baId":"e1a01c9a-73ae-11ec-9ad9-fa164ee08b71","projectCode":"2020-441900-41-03-033523","totalMoney":1200.0000,"fullName":"东莞市石碣镇经济发展局","finishDate":"2020-05-06","stateFlagName":"办结（通过）","projectName":"手机摄像头镜片自动化生产技术改造"},{"baId":"e1a2076f-73ae-11ec-9ad9-fa164ee08b71","projectCode":"2020-441900-49-03-033730","totalMoney":350.0000,"fullName":"东莞市横沥镇经济发展局","finishDate":"2020-05-06","stateFlagName":"办结（通过）","projectName":"北门公园（屋头山）"},{"baId":"e19fbd51-73ae-11ec-9ad9-fa164ee08b71","projectCode":"2020-441900-52-03-033026","totalMoney":350.0000,"fullName":"东莞市发展和改革局","finishDate":"2020-05-05","stateFlagName":"办结（通过）","projectName":"骅晋充电站（西平站）"},{"baId":"e18d0193-73ae-11ec-9ad9-fa164ee08b71","projectCode":"2020-441900-44-03-030886","totalMoney":300.0000,"fullName":"东莞市发展和改革局","finishDate":"2020-04-30","stateFlagName":"办结（通过）","projectName":"利利能建设长安镇安源同达电动汽车充电站"},{"baId":"e19544f4-73ae-11ec-9ad9-fa164ee08b71","projectCode":"2020-441900-37-03-028830","totalMoney":5546.3000,"fullName":"东莞市洪梅镇经济发展局","finishDate":"2020-04-30","stateFlagName":"办结（通过）","projectName":"研发中心建设项目"},{"baId":"e1955860-73ae-11ec-9ad9-fa164ee08b71","projectCode":"2020-441900-37-03-028807","totalMoney":3036.0100,"fullName":"东莞市洪梅镇经济发展局","finishDate":"2020-04-30","stateFlagName":"办结（通过）","projectName":"信息化建设项目"},{"baId":"e1979dee-73ae-11ec-9ad9-fa164ee08b71","projectCode":"2020-441900-17-03-033209","totalMoney":1500.0000,"fullName":"东莞市东坑镇工业信息科技局","finishDate":"2020-04-30","stateFlagName":"办结（通过）","projectName":"熔喷布自动化生产"},{"baId":"e19e32df-73ae-11ec-9ad9-fa164ee08b71","projectCode":"2020-441900-21-03-032719","totalMoney":36000.0000,"fullName":"东莞市东坑镇工业信息科技局","finishDate":"2020-04-30","stateFlagName":"办结（通过）","projectName":"国丰智能家具制造项目"},{"baId":"e19e9541-73ae-11ec-9ad9-fa164ee08b71","projectCode":"2020-441900-48-03-032657","totalMoney":192.3500,"fullName":"东莞市洪梅镇经济发展局","finishDate":"2020-04-30","stateFlagName":"办结（通过）","projectName":"洪梅镇洪屋涡村村道新建工程"},{"baId":"e1a034ef-73ae-11ec-9ad9-fa164ee08b71","projectCode":"2020-441900-44-03-033173","totalMoney":60000.0000,"fullName":"东莞市东坑镇工业信息科技局","finishDate":"2020-04-30","stateFlagName":"办结（通过）","projectName":"迈思普增资扩产项目"}],"pageNumber":575,"pageSize":15,"totalPage":641,"totalRow":9605,"firstPage":false,"lastPage":false},"message":"查询成功！","status":200}