[
  {
    "id": "2137000",
    "regionCode": "",
    "name": "全部",
    "parentId": "2137",
    "leaf": "1",
    "levelNum": "2",
    "standard": "1",
    "enabled": "1",
    "setYear": "2021",
    "operateDate": "Dec 25, 2019 8:46:30 PM",
    "path": "",
    "province": "",
    "localCity": ""
  },
  {
    "id": "2137001",
    "regionCode": "440001",
    "name": "省本级",
    "parentId": "2137",
    "leaf": "1",
    "levelNum": "2",
    "standard": "1",
    "enabled": "1",
    "setYear": "2021",
    "operateDate": "Dec 25, 2019 8:46:30 PM",
    "path": "广东省 省本级",
    "province": "广东省",
    "localCity": "省本级"
  },
  {
    "id": "2138",
    "regionCode": "440101",
    "name": "广州市",
    "parentId": "2137",
    "leaf": "0",
    "levelNum": "2",
    "standard": "1",
    "enabled": "1",
    "setYear": "2021",
    "operateDate": "Dec 25, 2019 8:46:30 PM",
    "path": "广东省 广州市",
    "province": "广东省 ",
    "localCity": "广州市",
    "children": [
      {
        "id": "2139",
        "regionCode": "440101",
        "name": "广州市市本级",
        "parentId": "2138",
        "leaf": "1",
        "levelNum": "3",
        "standard": "1",
        "enabled": "1",
        "setYear": "2021",
        "operateDate": "Dec 25, 2019 8:46:30 PM",
        "path": "广东省 广州市 市本级",
        "province": "广东省 ",
        "localCity": "广州市 "
      },
      {
        "id": "2141",
        "regionCode": "440104",
        "name": "越秀区",
        "parentId": "2138",
        "leaf": "1",
        "levelNum": "3",
        "standard": "1",
        "enabled": "1",
        "setYear": "2021",
        "operateDate": "Dec 25, 2019 8:46:30 PM",
        "path": "广东省 广州市 越秀区",
        "province": "广东省 ",
        "localCity": "广州市 "
      },
      {
        "id": "2142",
        "regionCode": "440105",
        "name": "海珠区",
        "parentId": "2138",
        "leaf": "1",
        "levelNum": "3",
        "standard": "1",
        "enabled": "1",
        "setYear": "2021",
        "operateDate": "Dec 25, 2019 8:46:30 PM",
        "path": "广东省 广州市 海珠区",
        "province": "广东省 ",
        "localCity": "广州市 "
      },
      {
        "id": "2140",
        "regionCode": "440103",
        "name": "荔湾区",
        "parentId": "2138",
        "leaf": "1",
        "levelNum": "3",
        "standard": "1",
        "enabled": "1",
        "setYear": "2021",
        "operateDate": "Dec 25, 2019 8:46:30 PM",
        "path": "广东省 广州市 荔湾区",
        "province": "广东省 ",
        "localCity": "广州市 "
      },
      {
        "id": "2143",
        "regionCode": "440106",
        "name": "天河区",
        "parentId": "2138",
        "leaf": "1",
        "levelNum": "3",
        "standard": "1",
        "enabled": "1",
        "setYear": "2021",
        "operateDate": "Dec 25, 2019 8:46:30 PM",
        "path": "广东省 广州市 天河区",
        "province": "广东省 ",
        "localCity": "广州市 "
      },
      {
        "id": "2144",
        "regionCode": "440111",
        "name": "白云区",
        "parentId": "2138",
        "leaf": "1",
        "levelNum": "3",
        "standard": "1",
        "enabled": "1",
        "setYear": "2021",
        "operateDate": "Dec 25, 2019 8:46:30 PM",
        "path": "广东省 广州市 白云区",
        "province": "广东省 ",
        "localCity": "广州市 "
      },
      {
        "id": "2145",
        "regionCode": "440112",
        "name": "黄埔区",
        "parentId": "2138",
        "leaf": "1",
        "levelNum": "3",
        "standard": "1",
        "enabled": "1",
        "setYear": "2021",
        "operateDate": "Dec 25, 2019 8:46:30 PM",
        "path": "广东省 广州市 黄埔区",
        "province": "广东省 ",
        "localCity": "广州市 "
      },
      {
        "id": "2147",
        "regionCode": "440114",
        "name": "花都区",
        "parentId": "2138",
        "leaf": "1",
        "levelNum": "3",
        "standard": "1",
        "enabled": "1",
        "setYear": "2021",
        "operateDate": "Dec 25, 2019 8:46:30 PM",
        "path": "广东省 广州市 花都区",
        "province": "广东省 ",
        "localCity": "广州市 "
      },
      {
        "id": "2146",
        "regionCode": "440113",
        "name": "番禺区",
        "parentId": "2138",
        "leaf": "1",
        "levelNum": "3",
        "standard": "1",
        "enabled": "1",
        "setYear": "2021",
        "operateDate": "Dec 25, 2019 8:46:30 PM",
        "path": "广东省 广州市 番禺区",
        "province": "广东省 ",
        "localCity": "广州市 "
      },
      {
        "id": "2148",
        "regionCode": "440115",
        "name": "南沙区",
        "parentId": "2138",
        "leaf": "1",
        "levelNum": "3",
        "standard": "1",
        "enabled": "1",
        "setYear": "2021",
        "operateDate": "Dec 25, 2019 8:46:30 PM",
        "path": "广东省 广州市 南沙区",
        "province": "广东省 ",
        "localCity": "广州市 "
      },
      {
        "id": "1245129DED264A5B8E234B7B35C1771D",
        "regionCode": "440117",
        "name": "从化区",
        "parentId": "2138",
        "leaf": "1",
        "remark": "2020-2区划",
        "levelNum": "3",
        "standard": "1",
        "enabled": "1",
        "setYear": "2021",
        "operateDate": "Jun 4, 2020 10:52:02 AM"
      },
      {
        "id": "D3B371D68A064546B7C534F88F7CD148",
        "regionCode": "440118",
        "name": "增城区",
        "parentId": "2138",
        "leaf": "1",
        "remark": "2020-2区划",
        "levelNum": "3",
        "standard": "1",
        "enabled": "1",
        "setYear": "2021",
        "operateDate": "Jun 4, 2020 10:53:01 AM"
      }
    ]
  },
  {
    "id": "2172",
    "regionCode": "440401",
    "name": "珠海市",
    "parentId": "2137",
    "leaf": "0",
    "levelNum": "2",
    "standard": "1",
    "enabled": "1",
    "setYear": "2021",
    "operateDate": "Dec 25, 2019 8:46:30 PM",
    "path": "广东省 珠海市",
    "province": "广东省 ",
    "localCity": "珠海市",
    "children": [
      {
        "id": "2173",
        "regionCode": "440401",
        "name": "珠海市市本级",
        "parentId": "2172",
        "leaf": "1",
        "levelNum": "3",
        "standard": "1",
        "enabled": "1",
        "setYear": "2021",
        "operateDate": "Dec 25, 2019 8:46:30 PM",
        "path": "广东省 珠海市 市本级",
        "province": "广东省 ",
        "localCity": "珠海市 "
      },
      {
        "id": "2174",
        "regionCode": "440402",
        "name": "香洲区",
        "parentId": "2172",
        "leaf": "1",
        "levelNum": "3",
        "standard": "1",
        "enabled": "1",
        "setYear": "2021",
        "operateDate": "Dec 25, 2019 8:46:30 PM",
        "path": "广东省 珠海市 香洲区",
        "province": "广东省 ",
        "localCity": "珠海市 "
      },
      {
        "id": "2175",
        "regionCode": "440403",
        "name": "斗门区",
        "parentId": "2172",
        "leaf": "1",
        "levelNum": "3",
        "standard": "1",
        "enabled": "1",
        "setYear": "2021",
        "operateDate": "Dec 25, 2019 8:46:30 PM",
        "path": "广东省 珠海市 斗门区",
        "province": "广东省 ",
        "localCity": "珠海市 "
      },
      {
        "id": "2176",
        "regionCode": "440404",
        "name": "金湾区",
        "parentId": "2172",
        "leaf": "1",
        "levelNum": "3",
        "standard": "1",
        "enabled": "1",
        "setYear": "2021",
        "operateDate": "Dec 25, 2019 8:46:30 PM",
        "path": "广东省 珠海市 金湾区",
        "province": "广东省 ",
        "localCity": "珠海市 "
      },
      {
        "id": "481D71EC85EC4E009A091E51C632EC55",
        "regionCode": "440441",
        "name": "高新区",
        "parentId": "2172",
        "leaf": "1",
        "remark": "2020-2区划",
        "levelNum": "3",
        "standard": "1",
        "enabled": "1",
        "setYear": "2021",
        "operateDate": "Jun 5, 2020 10:16:32 AM"
      },
      {
        "id": "8C3A6A6475BF4209AAAB81E894BBA390",
        "regionCode": "440443",
        "name": "高栏港经济区",
        "parentId": "2172",
        "leaf": "1",
        "remark": "2020-2区划",
        "levelNum": "3",
        "standard": "1",
        "enabled": "1",
        "setYear": "2021",
        "operateDate": "Jun 5, 2020 10:17:23 AM"
      },
      {
        "id": "26994BC454384D53A23C7DC011B40359",
        "regionCode": "440440",
        "name": "万山区",
        "parentId": "2172",
        "leaf": "1",
        "remark": "2020-2区划",
        "levelNum": "3",
        "standard": "1",
        "enabled": "1",
        "setYear": "2021",
        "operateDate": "Jun 5, 2020 10:15:59 AM"
      },
      {
        "id": "177BAE9522EE422798095DC0233ADD3C",
        "regionCode": "440444",
        "name": "保税区",
        "parentId": "2172",
        "leaf": "1",
        "remark": "2020-2区划",
        "levelNum": "3",
        "standard": "1",
        "enabled": "1",
        "setYear": "2021",
        "operateDate": "Jun 5, 2020 10:17:38 AM"
      }
    ]
  },
  {
    "id": "2177",
    "regionCode": "440501",
    "name": "汕头市",
    "parentId": "2137",
    "leaf": "0",
    "levelNum": "2",
    "standard": "1",
    "enabled": "1",
    "setYear": "2021",
    "operateDate": "Dec 25, 2019 8:46:30 PM",
    "path": "广东省 汕头市",
    "province": "广东省 ",
    "localCity": "汕头市",
    "children": [
      {
        "id": "2178",
        "regionCode": "440501",
        "name": "汕头市市本级",
        "parentId": "2177",
        "leaf": "1",
        "levelNum": "3",
        "standard": "1",
        "enabled": "1",
        "setYear": "2021",
        "operateDate": "Dec 25, 2019 8:46:30 PM",
        "path": "广东省 汕头市 市本级",
        "province": "广东省 ",
        "localCity": "汕头市 "
      },
      {
        "id": "2179",
        "regionCode": "440507",
        "name": "龙湖区",
        "parentId": "2177",
        "leaf": "1",
        "levelNum": "3",
        "standard": "1",
        "enabled": "1",
        "setYear": "2021",
        "operateDate": "Dec 25, 2019 8:46:30 PM",
        "path": "广东省 汕头市 龙湖区",
        "province": "广东省 ",
        "localCity": "汕头市 "
      },
      {
        "id": "2180",
        "regionCode": "440511",
        "name": "金平区",
        "parentId": "2177",
        "leaf": "1",
        "levelNum": "3",
        "standard": "1",
        "enabled": "1",
        "setYear": "2021",
        "operateDate": "Dec 25, 2019 8:46:30 PM",
        "path": "广东省 汕头市 金平区",
        "province": "广东省 ",
        "localCity": "汕头市 "
      },{
        "id": "2181",
        "regionCode": "440512",
        "name": "濠江区",
        "parentId": "2177",
        "leaf": "1",
        "levelNum": "3",
        "standard": "1",
        "enabled": "1",
        "setYear": "2021",
        "operateDate": "Dec 25, 2019 8:46:30 PM",
        "path": "广东省 汕头市 濠江区",
        "province": "广东省 ",
        "localCity": "汕头市 "
      },
      {
        "id": "2182",
        "regionCode": "440513",
        "name": "潮阳区",
        "parentId": "2177",
        "leaf": "1",
        "levelNum": "3",
        "standard": "1",
        "enabled": "1",
        "setYear": "2021",
        "operateDate": "Dec 25, 2019 8:46:30 PM",
        "path": "广东省 汕头市 潮阳区",
        "province": "广东省 ",
        "localCity": "汕头市 "
      },{
        "id": "2183",
        "regionCode": "440514",
        "name": "潮南区",
        "parentId": "2177",
        "leaf": "1",
        "levelNum": "3",
        "standard": "1",
        "enabled": "1",
        "setYear": "2021",
        "operateDate": "Dec 25, 2019 8:46:30 PM",
        "path": "广东省 汕头市 潮南区",
        "province": "广东省 ",
        "localCity": "汕头市 "
      },
      {
        "id": "2184",
        "regionCode": "440515",
        "name": "澄海区",
        "parentId": "2177",
        "leaf": "1",
        "levelNum": "3",
        "standard": "1",
        "enabled": "1",
        "setYear": "2021",
        "operateDate": "Dec 25, 2019 8:46:30 PM",
        "path": "广东省 汕头市 澄海区",
        "province": "广东省 ",
        "localCity": "汕头市 "
      },

      {
        "id": "2185",
        "regionCode": "440523",
        "name": "南澳县",
        "parentId": "2177",
        "leaf": "1",
        "levelNum": "3",
        "standard": "1",
        "enabled": "1",
        "setYear": "2021",
        "operateDate": "Dec 25, 2019 8:46:30 PM",
        "path": "广东省 汕头市 南澳县",
        "province": "广东省 ",
        "localCity": "汕头市 "
      },
      {
        "id": "2340",
        "regionCode": "440518",
        "name": "华侨经济文化合作试验区",
        "parentId": "2177",
        "leaf": "1",
        "levelNum": "3",
        "standard": "1",
        "enabled": "1",
        "setYear": "2021",
        "operateDate": "Dec 25, 2019 8:46:30 PM",
        "path": "广东省 汕头市 华侨经济文化合作试验区",
        "province": "广东省 ",
        "localCity": "汕头市 "
      }
    ]
  },
  {
    "id": "2186",
    "regionCode": "440601",
    "name": "佛山市",
    "parentId": "2137",
    "leaf": "0",
    "levelNum": "2",
    "standard": "1",
    "enabled": "1",
    "setYear": "2021",
    "operateDate": "Dec 25, 2019 8:46:30 PM",
    "path": "广东省 佛山市",
    "province": "广东省 ",
    "localCity": "佛山市",
    "children": [
      {
        "id": "2187",
        "regionCode": "440604",
        "name": "佛山市市本级",
        "parentId": "2186",
        "leaf": "1",
        "levelNum": "3",
        "standard": "1",
        "enabled": "1",
        "setYear": "2021",
        "operateDate": "Dec 25, 2019 8:46:30 PM",
        "path": "广东省 佛山市 市本级",
        "province": "广东省 ",
        "localCity": "佛山市 "
      },
      {
        "id": "2188",
        "regionCode": "440604",
        "name": "禅城区",
        "parentId": "2186",
        "leaf": "1",
        "levelNum": "3",
        "standard": "1",
        "enabled": "1",
        "setYear": "2021",
        "operateDate": "Dec 25, 2019 8:46:30 PM",
        "path": "广东省 佛山市 禅城区",
        "province": "广东省 ",
        "localCity": "佛山市 "
      },{
        "id": "2189",
        "regionCode": "440605",
        "name": "南海区",
        "parentId": "2186",
        "leaf": "1",
        "levelNum": "3",
        "standard": "1",
        "enabled": "1",
        "setYear": "2021",
        "operateDate": "Dec 25, 2019 8:46:30 PM",
        "path": "广东省 佛山市 南海区",
        "province": "广东省 ",
        "localCity": "佛山市 "
      },{
        "id": "2190",
        "regionCode": "440606",
        "name": "顺德区",
        "parentId": "2186",
        "leaf": "1",
        "levelNum": "3",
        "standard": "1",
        "enabled": "1",
        "setYear": "2021",
        "operateDate": "Dec 25, 2019 8:46:30 PM",
        "path": "广东省 佛山市 顺德区",
        "province": "广东省 ",
        "localCity": "佛山市 "
      },

      {
        "id": "2192",
        "regionCode": "440608",
        "name": "高明区",
        "parentId": "2186",
        "leaf": "1",
        "levelNum": "3",
        "standard": "1",
        "enabled": "1",
        "setYear": "2021",
        "operateDate": "Dec 25, 2019 8:46:30 PM",
        "path": "广东省 佛山市 高明区",
        "province": "广东省 ",
        "localCity": "佛山市 "
      },
      {
        "id": "2191",
        "regionCode": "440607",
        "name": "三水区",
        "parentId": "2186",
        "leaf": "1",
        "levelNum": "3",
        "standard": "1",
        "enabled": "1",
        "setYear": "2021",
        "operateDate": "Dec 25, 2019 8:46:30 PM",
        "path": "广东省 佛山市 三水区",
        "province": "广东省 ",
        "localCity": "佛山市 "
      }
    ]
  },
  {
    "id": "2152",
    "regionCode": "440201",
    "name": "韶关市",
    "parentId": "2137",
    "leaf": "0",
    "levelNum": "2",
    "standard": "1",
    "enabled": "1",
    "setYear": "2021",
    "operateDate": "Dec 25, 2019 8:46:30 PM",
    "path": "广东省 韶关市",
    "province": "广东省 ",
    "localCity": "韶关市",
    "children": [
      {
        "id": "2153",
        "regionCode": "440201",
        "name": "韶关市市本级",
        "parentId": "2152",
        "leaf": "1",
        "levelNum": "3",
        "standard": "1",
        "enabled": "1",
        "setYear": "2021",
        "operateDate": "Dec 25, 2019 8:46:30 PM",
        "path": "广东省 韶关市 市本级",
        "province": "广东省 ",
        "localCity": "韶关市 "
      },
      {
        "id": "2155",
        "regionCode": "440204",
        "name": "浈江区",
        "parentId": "2152",
        "leaf": "1",
        "levelNum": "3",
        "standard": "1",
        "enabled": "1",
        "setYear": "2021",
        "operateDate": "Dec 25, 2019 8:46:30 PM",
        "path": "广东省 韶关市 浈江区",
        "province": "广东省 ",
        "localCity": "韶关市 "
      },
      {
        "id": "2154",
        "regionCode": "440203",
        "name": "武江区",
        "parentId": "2152",
        "leaf": "1",
        "levelNum": "3",
        "standard": "1",
        "enabled": "1",
        "setYear": "2021",
        "operateDate": "Dec 25, 2019 8:46:30 PM",
        "path": "广东省 韶关市 武江区",
        "province": "广东省 ",
        "localCity": "韶关市 "
      },
      {
        "id": "2156",
        "regionCode": "440205",
        "name": "曲江区",
        "parentId": "2152",
        "leaf": "1",
        "levelNum": "3",
        "standard": "1",
        "enabled": "1",
        "setYear": "2021",
        "operateDate": "Dec 25, 2019 8:46:30 PM",
        "path": "广东省 韶关市 曲江区",
        "province": "广东省 ",
        "localCity": "韶关市 "
      },
      {
        "id": "2162",
        "regionCode": "440281",
        "name": "乐昌市",
        "parentId": "2152",
        "leaf": "1",
        "levelNum": "3",
        "standard": "1",
        "enabled": "1",
        "setYear": "2021",
        "operateDate": "Dec 25, 2019 8:46:30 PM",
        "path": "广东省 韶关市 乐昌市",
        "province": "广东省 ",
        "localCity": "韶关市 "
      },
      {
        "id": "2163",
        "regionCode": "440282",
        "name": "南雄市",
        "parentId": "2152",
        "leaf": "1",
        "levelNum": "3",
        "standard": "1",
        "enabled": "1",
        "setYear": "2021",
        "operateDate": "Dec 25, 2019 8:46:30 PM",
        "path": "广东省 韶关市 南雄市",
        "province": "广东省 ",
        "localCity": "韶关市 "
      },
      {
        "id": "2158",
        "regionCode": "440224",
        "name": "仁化县",
        "parentId": "2152",
        "leaf": "1",
        "levelNum": "3",
        "standard": "1",
        "enabled": "1",
        "setYear": "2021",
        "operateDate": "Dec 25, 2019 8:46:30 PM",
        "path": "广东省 韶关市 仁化县",
        "province": "广东省 ",
        "localCity": "韶关市 "
      },
      {
        "id": "2157",
        "regionCode": "440222",
        "name": "始兴县",
        "parentId": "2152",
        "leaf": "1",
        "levelNum": "3",
        "standard": "1",
        "enabled": "1",
        "setYear": "2021",
        "operateDate": "Dec 25, 2019 8:46:30 PM",
        "path": "广东省 韶关市 始兴县",
        "province": "广东省 ",
        "localCity": "韶关市 "
      },
      {
        "id": "2159",
        "regionCode": "440229",
        "name": "翁源县",
        "parentId": "2152",
        "leaf": "1",
        "levelNum": "3",
        "standard": "1",
        "enabled": "1",
        "setYear": "2021",
        "operateDate": "Dec 25, 2019 8:46:30 PM",
        "path": "广东省 韶关市 翁源县",
        "province": "广东省 ",
        "localCity": "韶关市 "
      },
      {
        "id": "2161",
        "regionCode": "440233",
        "name": "新丰县",
        "parentId": "2152",
        "leaf": "1",
        "levelNum": "3",
        "standard": "1",
        "enabled": "1",
        "setYear": "2021",
        "operateDate": "Dec 25, 2019 8:46:30 PM",
        "path": "广东省 韶关市 新丰县",
        "province": "广东省 ",
        "localCity": "韶关市 "
      },
      {
        "id": "2160",
        "regionCode": "440232",
        "name": "乳源瑶族自治区",
        "parentId": "2152",
        "leaf": "1",
        "levelNum": "3",
        "standard": "1",
        "enabled": "1",
        "setYear": "2021",
        "operateDate": "Dec 25, 2019 8:46:30 PM",
        "path": "广东省 韶关市 乳源瑶族自治区",
        "province": "广东省 ",
        "localCity": "韶关市 "
      },
      {
        "id": "c63a4a0d-49b1-11eb-b35f-fa163e098fbb",
        "regionCode": "440206000",
        "name": "韶关新区 ",
        "parentId": "2152",
        "leaf": "1",
        "levelNum": "3",
        "standard": "1",
        "enabled": "1",
        "setYear": "2021",
        "operateDate": "Dec 29, 2020 4:42:24 PM",
        "path": "广东省 韶关市 韶关新区",
        "province": "广东省 ",
        "localCity": "韶关市"
      }
    ]
  },
  {
    "id": "2254",
    "regionCode": "441601",
    "name": "河源市",
    "parentId": "2137",
    "leaf": "0",
    "levelNum": "2",
    "standard": "1",
    "enabled": "1",
    "setYear": "2021",
    "operateDate": "Dec 25, 2019 8:46:30 PM",
    "path": "广东省 河源市",
    "province": "广东省 ",
    "localCity": "河源市",
    "children": [
      {
        "id": "2255",
        "regionCode": "441601",
        "name": "河源市市本级",
        "parentId": "2254",
        "leaf": "1",
        "levelNum": "3",
        "standard": "1",
        "enabled": "1",
        "setYear": "2021",
        "operateDate": "Dec 25, 2019 8:46:30 PM",
        "path": "广东省 河源市 市本级",
        "province": "广东省 ",
        "localCity": "河源市 "
      },
      {
        "id": "2256",
        "regionCode": "441602",
        "name": "源城区",
        "parentId": "2254",
        "leaf": "1",
        "levelNum": "3",
        "standard": "1",
        "enabled": "1",
        "setYear": "2021",
        "operateDate": "Dec 25, 2019 8:46:30 PM",
        "path": "广东省 河源市 源城区",
        "province": "广东省 ",
        "localCity": "河源市 "
      },
      {
        "id": "2261",
        "regionCode": "441625",
        "name": "东源县",
        "parentId": "2254",
        "leaf": "1",
        "levelNum": "3",
        "standard": "1",
        "enabled": "1",
        "setYear": "2021",
        "operateDate": "Dec 25, 2019 8:46:30 PM",
        "path": "广东省 河源市 东源县",
        "province": "广东省 ",
        "localCity": "河源市 "
      },
      {
        "id": "2260",
        "regionCode": "441624",
        "name": "和平县",
        "parentId": "2254",
        "leaf": "1",
        "levelNum": "3",
        "standard": "1",
        "enabled": "1",
        "setYear": "2021",
        "operateDate": "Dec 25, 2019 8:46:30 PM",
        "path": "广东省 河源市 和平县",
        "province": "广东省 ",
        "localCity": "河源市 "
      },
      {
        "id": "2258",
        "regionCode": "441622",
        "name": "龙川县",
        "parentId": "2254",
        "leaf": "1",
        "levelNum": "3",
        "standard": "1",
        "enabled": "1",
        "setYear": "2021",
        "operateDate": "Dec 25, 2019 8:46:30 PM",
        "path": "广东省 河源市 龙川县",
        "province": "广东省 ",
        "localCity": "河源市 "
      },
      {
        "id": "2257",
        "regionCode": "441621",
        "name": "紫金县",
        "parentId": "2254",
        "leaf": "1",
        "levelNum": "3",
        "standard": "1",
        "enabled": "1",
        "setYear": "2021",
        "operateDate": "Dec 25, 2019 8:46:30 PM",
        "path": "广东省 河源市 紫金县",
        "province": "广东省 ",
        "localCity": "河源市 "
      },
      {
        "id": "2259",
        "regionCode": "441623",
        "name": "连平县",
        "parentId": "2254",
        "leaf": "1",
        "levelNum": "3",
        "standard": "1",
        "enabled": "1",
        "setYear": "2021",
        "operateDate": "Dec 25, 2019 8:46:30 PM",
        "path": "广东省 河源市 连平县",
        "province": "广东省 ",
        "localCity": "河源市 "
      },
      {
        "id": "19EB6EB37D374AE396C951227D1BFF28",
        "regionCode": "441640",
        "name": "江东新区",
        "parentId": "2254",
        "leaf": "1",
        "remark": "2020-2区划",
        "levelNum": "3",
        "standard": "1",
        "enabled": "1",
        "setYear": "2021",
        "operateDate": "Jun 5, 2020 10:28:01 AM"
      },
      {
        "id": "1cfbf3b8-49c5-11eb-b35f-fa163e098fbb",
        "regionCode": "441603000",
        "name": "高新区",
        "parentId": "2254",
        "leaf": "1",
        "levelNum": "3",
        "standard": "1",
        "enabled": "1",
        "setYear": "2021",
        "operateDate": "Dec 29, 2020 7:00:50 PM",
        "path": "广东省 河源市 高新区",
        "province": "广东省",
        "localCity": "河源市"
      }
    ]
  },
  {
    "id": "2238",
    "regionCode": "441401",
    "name": "梅州市",
    "parentId": "2137",
    "leaf": "0",
    "levelNum": "2",
    "standard": "1",
    "enabled": "1",
    "setYear": "2021",
    "operateDate": "Dec 25, 2019 8:46:30 PM",
    "path": "广东省 梅州市",
    "province": "广东省 ",
    "localCity": "梅州市",
    "children": [
      {
        "id": "2239",
        "regionCode": "441401",
        "name": "梅州市市本级",
        "parentId": "2238",
        "leaf": "1",
        "levelNum": "3",
        "standard": "1",
        "enabled": "1",
        "setYear": "2021",
        "operateDate": "Dec 25, 2019 8:46:30 PM",
        "path": "广东省 梅州市 市本级",
        "province": "广东省 ",
        "localCity": "梅州市 "
      },
      {
        "id": "2240",
        "regionCode": "441402",
        "name": "梅江区",
        "parentId": "2238",
        "leaf": "1",
        "levelNum": "3",
        "standard": "1",
        "enabled": "1",
        "setYear": "2021",
        "operateDate": "Dec 25, 2019 8:46:30 PM",
        "path": "广东省 梅州市 梅江区",
        "province": "广东省 ",
        "localCity": "梅州市 "
      },
      {
        "id": "2241",
        "regionCode": "441421",
        "name": "梅县区",
        "parentId": "2238",
        "leaf": "1",
        "levelNum": "3",
        "standard": "1",
        "enabled": "1",
        "setYear": "2021",
        "operateDate": "Dec 25, 2019 8:46:30 PM",
        "path": "广东省 梅州市 梅县区",
        "province": "广东省 ",
        "localCity": "梅州市 "
      },
      {
        "id": "2247",
        "regionCode": "441481",
        "name": "兴宁市",
        "parentId": "2238",
        "leaf": "1",
        "levelNum": "3",
        "standard": "1",
        "enabled": "1",
        "setYear": "2021",
        "operateDate": "Dec 25, 2019 8:46:30 PM",
        "path": "广东省 梅州市 兴宁市",
        "province": "广东省 ",
        "localCity": "梅州市 "
      },
      {
        "id": "2245",
        "regionCode": "441426",
        "name": "平远县",
        "parentId": "2238",
        "leaf": "1",
        "levelNum": "3",
        "standard": "1",
        "enabled": "1",
        "setYear": "2021",
        "operateDate": "Dec 25, 2019 8:46:30 PM",
        "path": "广东省 梅州市 平远县",
        "province": "广东省 ",
        "localCity": "梅州市 "
      },
      {
        "id": "2246",
        "regionCode": "441427",
        "name": "蕉岭县",
        "parentId": "2238",
        "leaf": "1",
        "levelNum": "3",
        "standard": "1",
        "enabled": "1",
        "setYear": "2021",
        "operateDate": "Dec 25, 2019 8:46:30 PM",
        "path": "广东省 梅州市 蕉岭县",
        "province": "广东省 ",
        "localCity": "梅州市 "
      },
      {
        "id": "2242",
        "regionCode": "441422",
        "name": "大埔县",
        "parentId": "2238",
        "leaf": "1",
        "levelNum": "3",
        "standard": "1",
        "enabled": "1",
        "setYear": "2021",
        "operateDate": "Dec 25, 2019 8:46:30 PM",
        "path": "广东省 梅州市 大埔县",
        "province": "广东省 ",
        "localCity": "梅州市 "
      },
      {
        "id": "2243",
        "regionCode": "441423",
        "name": "丰顺县",
        "parentId": "2238",
        "leaf": "1",
        "levelNum": "3",
        "standard": "1",
        "enabled": "1",
        "setYear": "2021",
        "operateDate": "Dec 25, 2019 8:46:30 PM",
        "path": "广东省 梅州市 丰顺县",
        "province": "广东省 ",
        "localCity": "梅州市 "
      },
      {
        "id": "2244",
        "regionCode": "441424",
        "name": "五华县",
        "parentId": "2238",
        "leaf": "1",
        "levelNum": "3",
        "standard": "1",
        "enabled": "1",
        "setYear": "2021",
        "operateDate": "Dec 25, 2019 8:46:30 PM",
        "path": "广东省 梅州市 五华县",
        "province": "广东省 ",
        "localCity": "梅州市 "
      }
    ]
  },
  {
    "id": "2231",
    "regionCode": "441301",
    "name": "惠州市",
    "parentId": "2137",
    "leaf": "0",
    "levelNum": "2",
    "standard": "1",
    "enabled": "1",
    "setYear": "2021",
    "operateDate": "Dec 25, 2019 8:46:30 PM",
    "path": "广东省 惠州市",
    "province": "广东省 ",
    "localCity": "惠州市",
    "children": [
      {
        "id": "2232",
        "regionCode": "441301",
        "name": "惠州市市本级",
        "parentId": "2231",
        "leaf": "1",
        "levelNum": "3",
        "standard": "1",
        "enabled": "1",
        "setYear": "2021",
        "operateDate": "Dec 25, 2019 8:46:30 PM",
        "path": "广东省 惠州市 市本级",
        "province": "广东省 ",
        "localCity": "惠州市 "
      },
      {
        "id": "2233",
        "regionCode": "441302",
        "name": "惠城区",
        "parentId": "2231",
        "leaf": "1",
        "levelNum": "3",
        "standard": "1",
        "enabled": "1",
        "setYear": "2021",
        "operateDate": "Dec 25, 2019 8:46:30 PM",
        "path": "广东省 惠州市 惠城区",
        "province": "广东省 ",
        "localCity": "惠州市 "
      },{
        "id": "2234",
        "regionCode": "441303",
        "name": "惠阳区",
        "parentId": "2231",
        "leaf": "1",
        "levelNum": "3",
        "standard": "1",
        "enabled": "1",
        "setYear": "2021",
        "operateDate": "Dec 25, 2019 8:46:30 PM",
        "path": "广东省 惠州市 惠阳区",
        "province": "广东省 ",
        "localCity": "惠州市 "
      },
      {
        "id": "2236",
        "regionCode": "441323",
        "name": "惠东县",
        "parentId": "2231",
        "leaf": "1",
        "levelNum": "3",
        "standard": "1",
        "enabled": "1",
        "setYear": "2021",
        "operateDate": "Dec 25, 2019 8:46:30 PM",
        "path": "广东省 惠州市 惠东县",
        "province": "广东省 ",
        "localCity": "惠州市 "
      },{
        "id": "2235",
        "regionCode": "441322",
        "name": "博罗县",
        "parentId": "2231",
        "leaf": "1",
        "levelNum": "3",
        "standard": "1",
        "enabled": "1",
        "setYear": "2021",
        "operateDate": "Dec 25, 2019 8:46:30 PM",
        "path": "广东省 惠州市 博罗县",
        "province": "广东省 ",
        "localCity": "惠州市 "
      },{
        "id": "2237",
        "regionCode": "441324",
        "name": "龙门县",
        "parentId": "2231",
        "leaf": "1",
        "levelNum": "3",
        "standard": "1",
        "enabled": "1",
        "setYear": "2021",
        "operateDate": "Dec 25, 2019 8:46:30 PM",
        "path": "广东省 惠州市 龙门县",
        "province": "广东省 ",
        "localCity": "惠州市 "
      },{
        "id": "53AEFFF36C524ADD949E419CF460EA7F",
        "regionCode": "441340",
        "name": "大亚湾经济开发区",
        "parentId": "2231",
        "leaf": "1",
        "remark": "2020-2区划",
        "levelNum": "3",
        "standard": "1",
        "enabled": "1",
        "setYear": "2021",
        "operateDate": "Jun 5, 2020 10:22:34 AM"
      },
      {
        "id": "4138D7FEED874228BBA15031B9E71FD1",
        "regionCode": "441341",
        "name": "惠州仲恺高新技术产业开发区",
        "parentId": "2231",
        "leaf": "1",
        "remark": "2020-2区划",
        "levelNum": "3",
        "standard": "1",
        "enabled": "1",
        "setYear": "2021",
        "operateDate": "Jun 5, 2020 10:22:53 AM"
      }

    ]
  },
  {
    "id": "2248",
    "regionCode": "441501",
    "name": "汕尾市",
    "parentId": "2137",
    "leaf": "0",
    "levelNum": "2",
    "standard": "1",
    "enabled": "1",
    "setYear": "2021",
    "operateDate": "Dec 25, 2019 8:46:30 PM",
    "path": "广东省 汕尾市",
    "province": "广东省 ",
    "localCity": "汕尾市",
    "children": [
      {
        "id": "2249",
        "regionCode": "441501",
        "name": "汕尾市市本级",
        "parentId": "2248",
        "leaf": "1",
        "levelNum": "3",
        "standard": "1",
        "enabled": "1",
        "setYear": "2021",
        "operateDate": "Dec 25, 2019 8:46:30 PM",
        "path": "广东省 汕尾市 市本级",
        "province": "广东省 ",
        "localCity": "汕尾市 "
      },
      {
        "id": "2250",
        "regionCode": "441502",
        "name": "城区",
        "parentId": "2248",
        "leaf": "1",
        "levelNum": "3",
        "standard": "1",
        "enabled": "1",
        "setYear": "2021",
        "operateDate": "Dec 25, 2019 8:46:30 PM",
        "path": "广东省 汕尾市 城区",
        "province": "广东省 ",
        "localCity": "汕尾市 "
      },
      {
        "id": "2251",
        "regionCode": "441521",
        "name": "海丰县",
        "parentId": "2248",
        "leaf": "1",
        "levelNum": "3",
        "standard": "1",
        "enabled": "1",
        "setYear": "2021",
        "operateDate": "Dec 25, 2019 8:46:30 PM",
        "path": "广东省 汕尾市 海丰县",
        "province": "广东省 ",
        "localCity": "汕尾市 "
      },
      {
        "id": "2253",
        "regionCode": "441581",
        "name": "陆丰市",
        "parentId": "2248",
        "leaf": "1",
        "levelNum": "3",
        "standard": "1",
        "enabled": "1",
        "setYear": "2021",
        "operateDate": "Dec 25, 2019 8:46:30 PM",
        "path": "广东省 汕尾市 陆丰市",
        "province": "广东省 ",
        "localCity": "汕尾市 "
      },
      {
        "id": "2252",
        "regionCode": "441523",
        "name": "陆河县",
        "parentId": "2248",
        "leaf": "1",
        "levelNum": "3",
        "standard": "1",
        "enabled": "1",
        "setYear": "2021",
        "operateDate": "Dec 25, 2019 8:46:30 PM",
        "path": "广东省 汕尾市 陆河县",
        "province": "广东省 ",
        "localCity": "汕尾市 "
      },
      {
        "id": "0D1C6EDF1EB14DF8B0D466F070026A4C",
        "regionCode": "441540",
        "name": "红海湾开发区",
        "parentId": "2248",
        "leaf": "1",
        "remark": "2020-2区划",
        "levelNum": "3",
        "standard": "1",
        "enabled": "1",
        "setYear": "2021",
        "operateDate": "Jun 5, 2020 10:25:34 AM"
      },
      {
        "id": "0909739056B5427794C89F7D5B881C9D",
        "regionCode": "441542",
        "name": "华侨管理区",
        "parentId": "2248",
        "leaf": "1",
        "remark": "2020-2区划",
        "levelNum": "3",
        "standard": "1",
        "enabled": "1",
        "setYear": "2021",
        "operateDate": "Jun 5, 2020 10:26:03 AM"
      },
      {
        "id": "688F0FE7A4BD4E96BF5B36EEC7D27799",
        "regionCode": "441541",
        "name": "新区管理委员会",
        "parentId": "2248",
        "leaf": "1",
        "remark": "2020-2区划",
        "levelNum": "3",
        "standard": "1",
        "enabled": "1",
        "setYear": "2021",
        "operateDate": "Jun 5, 2020 10:25:49 AM"
      }
    ]
  },
  {
    "id": "2278",
    "regionCode": "441901",
    "name": "东莞市",
    "parentId": "2137",
    "leaf": "0",
    "levelNum": "2",
    "standard": "1",
    "enabled": "1",
    "setYear": "2021",
    "operateDate": "Jan 14, 2021 5:11:16 PM",
    "path": "广东省 东莞市",
    "province": "广东省 ",
    "localCity": "东莞市",
    "children": [
      {
        "id": "c668fb1c-49b1-11eb-b35f-fa163e098fcc",
        "regionCode": "441901",
        "name": "东莞市市本级 ",
        "parentId": "2278",
        "leaf": "1",
        "levelNum": "3",
        "standard": "1",
        "enabled": "1",
        "setYear": "2021",
        "operateDate": "Dec 29, 2020 4:42:25 PM",
        "path": "广东省 东莞市 市本级",
        "province": "广东省 ",
        "localCity": "东莞市"
      },
      {
        "id": "c650caba-49b1-11eb-b35f-fa163e098fbb",
        "regionCode": "441900009",
        "name": "松山湖园区 ",
        "parentId": "2278",
        "leaf": "1",
        "levelNum": "3",
        "standard": "1",
        "enabled": "1",
        "setYear": "2021",
        "operateDate": "Dec 29, 2020 4:42:25 PM",
        "path": "广东省 东莞市 松山湖园区",
        "province": "广东省 ",
        "localCity": "东莞市"
      },
      {
        "id": "c668fb1c-49b1-11eb-b35f-fa163e098fbb",
        "regionCode": "441900005",
        "name": "莞城街道 ",
        "parentId": "2278",
        "leaf": "1",
        "levelNum": "3",
        "standard": "1",
        "enabled": "1",
        "setYear": "2021",
        "operateDate": "Dec 29, 2020 4:42:25 PM",
        "path": "广东省 东莞市 莞城街道",
        "province": "广东省 ",
        "localCity": "东莞市"
      },
      {
        "id": "c64d7e93-49b1-11eb-b35f-fa163e098fbb",
        "regionCode": "441900002",
        "name": "东城街道 ",
        "parentId": "2278",
        "leaf": "1",
        "levelNum": "3",
        "standard": "1",
        "enabled": "1",
        "setYear": "2021",
        "operateDate": "Dec 29, 2020 4:42:24 PM",
        "path": "广东省 东莞市 东城街道",
        "province": "广东省 ",
        "localCity": "东莞市"
      },
      {
        "id": "c6526343-49b1-11eb-b35f-fa163e098fbb",
        "regionCode": "441900004",
        "name": "万江街道 ",
        "parentId": "2278",
        "leaf": "1",
        "levelNum": "3",
        "standard": "1",
        "enabled": "1",
        "setYear": "2021",
        "operateDate": "Dec 29, 2020 4:42:25 PM",
        "path": "广东省 东莞市 万江街道",
        "province": "广东省 ",
        "localCity": "东莞市"
      },
      {
        "id": "c64f25b0-49b1-11eb-b35f-fa163e098fbb",
        "regionCode": "441900003",
        "name": "南城街道 ",
        "parentId": "2278",
        "leaf": "1",
        "levelNum": "3",
        "standard": "1",
        "enabled": "1",
        "setYear": "2021",
        "operateDate": "Dec 29, 2020 4:42:25 PM",
        "path": "广东省 东莞市 南城街道",
        "province": "广东省 ",
        "localCity": "东莞市"
      },
      {
        "id": "c660c277-49b1-11eb-b35f-fa163e098fbb",
        "regionCode": "441900028",
        "name": "虎门镇 ",
        "parentId": "2278",
        "leaf": "1",
        "levelNum": "3",
        "standard": "1",
        "enabled": "1",
        "setYear": "2021",
        "operateDate": "Dec 29, 2020 4:42:25 PM",
        "path": "广东省 东莞市 虎门镇",
        "province": "广东省 ",
        "localCity": "东莞市"
      },
      {
        "id": "c66dee20-49b1-11eb-b35f-fa163e098fbb",
        "regionCode": "441900007",
        "name": "石龙镇 ",
        "parentId": "2278",
        "leaf": "1",
        "levelNum": "3",
        "standard": "1",
        "enabled": "1",
        "setYear": "2021",
        "operateDate": "Dec 29, 2020 4:42:25 PM",
        "path": "广东省 东莞市 石龙镇",
        "province": "广东省 ",
        "localCity": "东莞市"
      },
      {
        "id": "c66a9d7f-49b1-11eb-b35f-fa163e098fbb",
        "regionCode": "441900035",
        "name": "中堂镇 ",
        "parentId": "2278",
        "leaf": "1",
        "levelNum": "3",
        "standard": "1",
        "enabled": "1",
        "setYear": "2021",
        "operateDate": "Dec 29, 2020 4:42:25 PM",
        "path": "广东省 东莞市 中堂镇",
        "province": "广东省 ",
        "localCity": "东莞市"
      },
      {
        "id": "c6674754-49b1-11eb-b35f-fa163e098fbb",
        "regionCode": "441900034",
        "name": "望牛墩镇 ",
        "parentId": "2278",
        "leaf": "1",
        "levelNum": "3",
        "standard": "1",
        "enabled": "1",
        "setYear": "2021",
        "operateDate": "Dec 29, 2020 4:42:25 PM",
        "path": "广东省 东莞市 望牛墩镇",
        "province": "广东省 ",
        "localCity": "东莞市"
      },
      {
        "id": "c6627c8b-49b1-11eb-b35f-fa163e098fbb",
        "regionCode": "441900031",
        "name": "道滘镇 ",
        "parentId": "2278",
        "leaf": "1",
        "levelNum": "3",
        "standard": "1",
        "enabled": "1",
        "setYear": "2021",
        "operateDate": "Dec 29, 2020 4:42:25 PM",
        "path": "广东省 东莞市 道滘镇",
        "province": "广东省 ",
        "localCity": "东莞市"
      },
      {
        "id": "c655f707-49b1-11eb-b35f-fa163e098fbb",
        "regionCode": "441900032",
        "name": "洪梅镇 ",
        "parentId": "2278",
        "leaf": "1",
        "levelNum": "3",
        "standard": "1",
        "enabled": "1",
        "setYear": "2021",
        "operateDate": "Dec 29, 2020 4:42:25 PM",
        "path": "广东省 东莞市 洪梅镇",
        "province": "广东省 ",
        "localCity": "东莞市"
      },
      {
        "id": "c648a386-49b1-11eb-b35f-fa163e098fbb",
        "regionCode": "441900033",
        "name": "麻涌镇 ",
        "parentId": "2278",
        "leaf": "1",
        "levelNum": "3",
        "standard": "1",
        "enabled": "1",
        "setYear": "2021",
        "operateDate": "Dec 29, 2020 4:42:24 PM",
        "path": "广东省 东莞市 麻涌镇",
        "province": "广东省 ",
        "localCity": "东莞市"
      },
      {
        "id": "c64708ac-49b1-11eb-b35f-fa163e098fbb",

        "regionCode": "441900027",
        "name": "长安镇 ",
        "parentId": "2278",
        "leaf": "1",
        "levelNum": "3",
        "standard": "1",
        "enabled": "1",
        "setYear": "2021",
        "operateDate": "Dec 29, 2020 4:42:24 PM",
        "path": "广东省 东莞市 长安镇",
        "province": "广东省 ",
        "localCity": "东莞市"
      },
      {
        "id": "c65d39aa-49b1-11eb-b35f-fa163e098fbb",
        "regionCode": "441900029",
        "name": "厚街镇 ",
        "parentId": "2278",
        "leaf": "1",
        "levelNum": "3",
        "standard": "1",
        "enabled": "1",
        "setYear": "2021",
        "operateDate": "Dec 29, 2020 4:42:25 PM",
        "path": "广东省 东莞市 厚街镇",
        "province": "广东省 ",
        "localCity": "东莞市"
      },
      {
        "id": "c65b94da-49b1-11eb-b35f-fa163e098fbb",
        "regionCode": "441900030",
        "name": "沙田镇 ",
        "parentId": "2278",
        "leaf": "1",
        "levelNum": "3",
        "standard": "1",
        "enabled": "1",
        "setYear": "2021",
        "operateDate": "Dec 29, 2020 4:42:25 PM",
        "path": "广东省 东莞市 沙田镇",
        "province": "广东省 ",
        "localCity": "东莞市"
      },
      {
        "id": "5DA6FB7BF9F24CCEB84FF1C322160B02",
        "regionCode": "441900019",
        "name": "寮步镇",
        "parentId": "2278",
        "leaf": "1",
        "levelNum": "3",
        "standard": "1",
        "enabled": "1",
        "setYear": "2021",
        "operateDate": "Jan 14, 2021 8:17:05 PM"
      },
      {
        "id": "917D6E42CAC647F1AC2DC3A312733339",
        "regionCode": "441900026",
        "name": "大岭山镇",
        "parentId": "2278",
        "leaf": "1",
        "levelNum": "3",
        "standard": "1",
        "enabled": "1",
        "setYear": "2021",
        "operateDate": "Jan 14, 2021 8:13:38 PM"
      },
      {
        "id": "c6544277-49b1-11eb-b35f-fa163e098fbb",
        "regionCode": "441900021",
        "name": "大朗镇 ",
        "parentId": "2278",
        "leaf": "1",
        "levelNum": "3",
        "standard": "1",
        "enabled": "1",
        "setYear": "2021",
        "operateDate": "Dec 29, 2020 4:42:25 PM",
        "path": "广东省 东莞市 大朗镇",
        "province": "广东省 ",
        "localCity": "东莞市"
      },
      {
        "id": "c67006f8-49b1-11eb-b35f-fa163e098fbb",
        "regionCode": "441900022",
        "name": "黄江镇 ",
        "parentId": "2278",
        "leaf": "1",
        "levelNum": "3",
        "standard": "1",
        "enabled": "1",
        "setYear": "2021",
        "operateDate": "Dec 29, 2020 4:42:25 PM",
        "path": "广东省 东莞市 黄江镇",
        "province": "广东省 ",
        "localCity": "东莞市"
      },
      {
        "id": "B73A899E365E4937BC52CD22951F3A8D",
        "regionCode": "441900023",
        "name": "清溪镇",
        "parentId": "2278",
        "leaf": "1",
        "levelNum": "3",
        "standard": "1",
        "enabled": "1",
        "setYear": "2021",
        "operateDate": "Jan 14, 2021 8:15:18 PM"
      },
      {
        "id": "c64a39b9-49b1-11eb-b35f-fa163e098fbb",
        "regionCode": "441900020",
        "name": "樟木头镇 ",
        "parentId": "2278",
        "leaf": "1",
        "levelNum": "3",
        "standard": "1",
        "enabled": "1",
        "setYear": "2021",
        "operateDate": "Dec 29, 2020 4:42:24 PM",
        "path": "广东省 东莞市 樟木头镇",
        "province": "广东省 ",
        "localCity": "东莞市"
      },
      {
        "id": "c6641cc8-49b1-11eb-b35f-fa163e098fbb",
        "regionCode": "441900024",
        "name": "塘厦镇 ",
        "parentId": "2278",
        "leaf": "1",
        "levelNum": "3",
        "standard": "1",
        "enabled": "1",
        "setYear": "2021",
        "operateDate": "Dec 29, 2020 4:42:25 PM",
        "path": "广东省 东莞市 塘厦镇",
        "province": "广东省 ",
        "localCity": "东莞市"
      },
      {
        "id": "0FD2DBDD3EE843B59268ECC051DCB81D",
        "regionCode": "441900025",
        "name": "凤岗镇",
        "parentId": "2278",
        "leaf": "1",
        "levelNum": "3",
        "standard": "1",
        "enabled": "1",
        "setYear": "2021",
        "operateDate": "Jan 14, 2021 8:18:32 PM"
      },
      {
        "id": "c665a6c5-49b1-11eb-b35f-fa163e098fbb",
        "regionCode": "441900016",
        "name": "谢岗镇 ",
        "parentId": "2278",
        "leaf": "1",
        "levelNum": "3",
        "standard": "1",
        "enabled": "1",
        "setYear": "2021",
        "operateDate": "Dec 29, 2020 4:42:25 PM",
        "path": "广东省 东莞市 谢岗镇",
        "province": "广东省 ",
        "localCity": "东莞市"
      },
      {
        "id": "c6456d4a-49b1-11eb-b35f-fa163e098fbb",
        "regionCode": "441900018",
        "name": "常平镇 ",
        "parentId": "2278",
        "leaf": "1",
        "levelNum": "3",
        "standard": "1",
        "enabled": "1",
        "setYear": "2021",
        "operateDate": "Dec 29, 2020 4:42:24 PM",
        "path": "广东省 东莞市 常平镇",
        "province": "广东省 ",
        "localCity": "东莞市"
      },
      {
        "id": "c657ed8b-49b1-11eb-b35f-fa163e098fbb",
        "regionCode": "441900015",
        "name": "桥头镇 ",
        "parentId": "2278",
        "leaf": "1",
        "levelNum": "3",
        "standard": "1",
        "enabled": "1",
        "setYear": "2021",
        "operateDate": "Dec 29, 2020 4:42:25 PM",
        "path": "广东省 东莞市 桥头镇",
        "province": "广东省 ",
        "localCity": "东莞市"
      },
      {
        "id": "C7BD23A070FD4DB6B2FB24ED268A62A9",
        "regionCode": "441900014",
        "name": "横沥镇",
        "parentId": "2278",
        "leaf": "1",
        "levelNum": "3",
        "standard": "1",
        "enabled": "1",
        "setYear": "2021",
        "operateDate": "Jan 14, 2021 8:15:50 PM"
      },
      {
        "id": "c643c6fd-49b1-11eb-b35f-fa163e098fbb",
        "regionCode": "441900017",
        "name": "东坑镇 ",
        "parentId": "2278",
        "leaf": "1",
        "levelNum": "3",
        "standard": "1",
        "enabled": "1",
        "setYear": "2021",
        "operateDate": "Dec 29, 2020 4:42:24 PM",
        "path": "广东省 东莞市 东坑镇",
        "province": "广东省 ",
        "localCity": "东莞市"
      },
      {
        "id": "c66c3fa5-49b1-11eb-b35f-fa163e098fbb",
        "regionCode": "441900013",
        "name": "企石镇 ",
        "parentId": "2278",
        "leaf": "1",
        "levelNum": "3",
        "standard": "1",
        "enabled": "1",
        "setYear": "2021",
        "operateDate": "Dec 29, 2020 4:42:25 PM",
        "path": "广东省 东莞市 企石镇",
        "province": "广东省 ",
        "localCity": "东莞市"
      },
      {
        "id": "c64bdd7f-49b1-11eb-b35f-fa163e098fbb",
        "regionCode": "441900012",
        "name": "石排镇 ",
        "parentId": "2278",
        "leaf": "1",
        "levelNum": "3",
        "standard": "1",
        "enabled": "1",
        "setYear": "2021",
        "operateDate": "Dec 29, 2020 4:42:24 PM",
        "path": "广东省 东莞市 石排镇",
        "province": "广东省 ",
        "localCity": "东莞市"
      },
      {
        "id": "c659d315-49b1-11eb-b35f-fa163e098fbb",
        "regionCode": "441900008",
        "name": "茶山镇 ",
        "parentId": "2278",
        "leaf": "1",
        "levelNum": "3",
        "standard": "1",
        "enabled": "1",
        "setYear": "2021",
        "operateDate": "Dec 29, 2020 4:42:25 PM",
        "path": "广东省 东莞市 茶山镇",
        "province": "广东省 ",
        "localCity": "东莞市"
      },
      {
        "id": "c641fd7d-49b1-11eb-b35f-fa163e098fbb",
        "regionCode": "441900006",
        "name": "石碣镇 ",
        "parentId": "2278",
        "leaf": "1",
        "levelNum": "3",
        "standard": "1",
        "enabled": "1",
        "setYear": "2021",
        "operateDate": "Dec 29, 2020 4:42:24 PM",
        "path": "广东省 东莞市 石碣镇",
        "province": "广东省 ",
        "localCity": "东莞市"
      },
      {
        "id": "B6FCB6BF45F34B2AA55843E6241A09E1",
        "regionCode": "441900036",
        "name": "高埗镇",
        "parentId": "2278",
        "leaf": "1",
        "levelNum": "3",
        "standard": "1",
        "enabled": "1",
        "setYear": "2021",
        "operateDate": "Jan 14, 2021 8:18:08 PM"
      },
      {
        "id": "1cffcc00-49c5-11eb-b35f-fa163e098fbb",
        "regionCode": "441900011",
        "name": "滨海湾新区",
        "parentId": "2278",
        "leaf": "1",
        "levelNum": "3",
        "standard": "1",
        "enabled": "1",
        "setYear": "2021",
        "operateDate": "Dec 29, 2020 7:00:50 PM",
        "path": "广东省 东莞市 滨海湾新区",
        "province": "广东省",
        "localCity": "东莞市"
      },
      {
        "id": "1d01a215-49c5-11eb-b35f-fa163e098fbb",
        "regionCode": "441900010",
        "name": "水乡",
        "parentId": "2278",
        "leaf": "1",
        "levelNum": "3",
        "standard": "1",
        "enabled": "1",
        "setYear": "2021",
        "operateDate": "Dec 29, 2020 7:00:50 PM",
        "path": "广东省 东莞市 水乡",
        "province": "广东省",
        "localCity": "东莞市"
      }
    ]
  },
  {
    "id": "2279",
    "regionCode": "442000",
    "name": "中山市",
    "parentId": "2137",
    "leaf": "1",
    "levelNum": "2",
    "standard": "1",
    "enabled": "1",
    "setYear": "2021",
    "operateDate": "Dec 25, 2019 8:46:30 PM",
    "path": "广东省 中山市",
    "province": "广东省 ",
    "localCity": "中山市",
    "children": [
      {
        "id": "1d01a215-49c5-2100",
        "regionCode": "442000",
        "name": "中山市市本级",
        "parentId": "2279",
        "leaf": "1",
        "levelNum": "3",
        "standard": "1",
        "enabled": "1",
        "setYear": "2021",
        "operateDate": "Dec 25, 2019 8:46:30 PM"
      },
      {
        "id": "1d01a215-49c5-2197",
        "regionCode": "442000001",
        "name": "石岐街道",
        "parentId": "2279",
        "leaf": "1",
        "levelNum": "3",
        "standard": "1",
        "enabled": "1",
        "setYear": "2021",
        "operateDate": "Dec 25, 2019 8:46:30 PM"
      },
      {
        "id": "1d01a215-49c5-2200",
        "regionCode": "442000002",
        "name": "东区街道",
        "parentId": "2279",
        "leaf": "1",
        "levelNum": "3",
        "standard": "1",
        "enabled": "1",
        "setYear": "2021",
        "operateDate": "Dec 25, 2019 8:46:30 PM"
      },
      {
        "id": "1d01a215-49c5-2199",
        "regionCode": "442000003",
        "name": "火炬区",
        "parentId": "2279",
        "leaf": "1",
        "levelNum": "3",
        "standard": "1",
        "enabled": "1",
        "setYear": "2021",
        "operateDate": "Dec 25, 2019 8:46:30 PM"
      },
      {
        "id": "1d01a215-49c5-2198",
        "regionCode": "442000004",
        "name": "西区街道",
        "parentId": "2279",
        "leaf": "1",
        "levelNum": "3",
        "standard": "1",
        "enabled": "1",
        "setYear": "2021",
        "operateDate": "Dec 25, 2019 8:46:30 PM"
      },
      {
        "id": "1d01a215-49c5-2195",
        "regionCode": "442000005",
        "name": "南区街道",
        "parentId": "2279",
        "leaf": "1",
        "levelNum": "3",
        "standard": "1",
        "enabled": "1",
        "setYear": "2021",
        "operateDate": "Dec 25, 2019 8:46:30 PM"
      },
      {
        "id": "1d01a215-49c5-2196",
        "regionCode": "442000100",
        "name": "小榄镇",
        "parentId": "2279",
        "leaf": "1",
        "levelNum": "3",
        "standard": "1",
        "enabled": "1",
        "setYear": "2021",
        "operateDate": "Dec 25, 2019 8:46:30 PM"
      },
      {
        "id": "1d01a215-49c5-2201",
        "regionCode": "442000101",
        "name": "黄圃镇",
        "parentId": "2279",
        "leaf": "1",
        "levelNum": "3",
        "standard": "1",
        "enabled": "1",
        "setYear": "2021",
        "operateDate": "Dec 25, 2019 8:46:30 PM"
      },
      {
        "id": "1d01a215-49c5-3200",
        "regionCode": "442000103",
        "name": "东凤镇",
        "parentId": "2279",
        "leaf": "1",
        "levelNum": "3",
        "standard": "1",
        "enabled": "1",
        "setYear": "2021",
        "operateDate": "Dec 25, 2019 8:46:30 PM"
      },
      {
        "id": "1d01a215-49c5-3198",
        "regionCode": "442000105",
        "name": "古镇镇",
        "parentId": "2279",
        "leaf": "1",
        "levelNum": "3",
        "standard": "1",
        "enabled": "1",
        "setYear": "2021",
        "operateDate": "Dec 25, 2019 8:46:30 PM"
      },
      {
        "id": "1d01a215-49c5-3195",
        "regionCode": "442000106",
        "name": "沙溪镇",
        "parentId": "2279",
        "leaf": "1",
        "levelNum": "3",
        "standard": "1",
        "enabled": "1",
        "setYear": "2021",
        "operateDate": "Dec 25, 2019 8:46:30 PM"
      },
      {
        "id": "1d01a215-49c5-3196",
        "regionCode": "442000107",
        "name": "坦洲镇",
        "parentId": "2279",
        "leaf": "1",
        "levelNum": "3",
        "standard": "1",
        "enabled": "1",
        "setYear": "2021",
        "operateDate": "Dec 25, 2019 8:46:30 PM"
      },
      {
        "id": "1d01a215-49c5-3196",
        "regionCode": "442000108",
        "name": "港口镇",
        "parentId": "2279",
        "leaf": "1",
        "levelNum": "3",
        "standard": "1",
        "enabled": "1",
        "setYear": "2021",
        "operateDate": "Dec 25, 2019 8:46:30 PM"
      },
      {
        "id": "1d01a215-49c5-3201",
        "regionCode": "442000109",
        "name": "三角镇",
        "parentId": "2279",
        "leaf": "1",
        "levelNum": "3",
        "standard": "1",
        "enabled": "1",
        "setYear": "2021",
        "operateDate": "Dec 25, 2019 8:46:30 PM"
      },
      {
        "id": "1d01a215-49c5-3197",
        "regionCode": "442000110",
        "name": "横栏镇",
        "parentId": "2279",
        "leaf": "1",
        "levelNum": "3",
        "standard": "1",
        "enabled": "1",
        "setYear": "2021",
        "operateDate": "Dec 25, 2019 8:46:30 PM"
      },
      {
        "id": "1d01a215-49c5-4200",
        "regionCode": "442000111",
        "name": "南头镇",
        "parentId": "2279",
        "leaf": "1",
        "levelNum": "3",
        "standard": "1",
        "enabled": "1",
        "setYear": "2021",
        "operateDate": "Dec 25, 2019 8:46:30 PM"
      },
      {
        "id": "1d01a215-49c5-4199",
        "regionCode": "442000112",
        "name": "阜沙镇",
        "parentId": "2279",
        "leaf": "1",
        "levelNum": "3",
        "standard": "1",
        "enabled": "1",
        "setYear": "2021",
        "operateDate": "Dec 25, 2019 8:46:30 PM"
      },
      {
        "id": "1d01a215-49c5-4195",
        "regionCode": "442000114",
        "name": "三乡镇",
        "parentId": "2279",
        "leaf": "1",
        "levelNum": "3",
        "standard": "1",
        "enabled": "1",
        "setYear": "2021",
        "operateDate": "Dec 25, 2019 8:46:30 PM"
      },
      {
        "id": "1d01a215-49c5-4196",
        "regionCode": "442000115",
        "name": "板芙镇",
        "parentId": "2279",
        "leaf": "1",
        "levelNum": "3",
        "standard": "1",
        "enabled": "1",
        "setYear": "2021",
        "operateDate": "Dec 25, 2019 8:46:30 PM"
      },
      {
        "id": "1d01a215-49c5-5200",
        "regionCode": "442000116",
        "name": "大涌镇",
        "parentId": "2279",
        "leaf": "1",
        "levelNum": "3",
        "standard": "1",
        "enabled": "1",
        "setYear": "2021",
        "operateDate": "Dec 25, 2019 8:46:30 PM"
      },
      {
        "id": "1d01a215-49c5-5199",
        "regionCode": "442000117",
        "name": "神湾镇",
        "parentId": "2279",
        "leaf": "1",
        "levelNum": "3",
        "standard": "1",
        "enabled": "1",
        "setYear": "2021",
        "operateDate": "Dec 25, 2019 8:46:30 PM"
      },
      {
        "id": "1d01a215-49c5-5198",
        "regionCode": "442000118",
        "name": "五桂山街道",
        "parentId": "2279",
        "leaf": "1",
        "levelNum": "3",
        "standard": "1",
        "enabled": "1",
        "setYear": "2021",
        "operateDate": "Dec 25, 2019 8:46:30 PM"
      },
      {
        "id": "1d01a215-49c5-5195",
        "regionCode": "442000006",
        "name": "翠亨新区",
        "parentId": "2279",
        "leaf": "1",
        "levelNum": "3",
        "standard": "1",
        "enabled": "1",
        "setYear": "2021",
        "operateDate": "Dec 25, 2019 8:46:30 PM"
      }
    ]
  },
  {
    "id": "2193",
    "regionCode": "440701",
    "name": "江门市",
    "parentId": "2137",
    "leaf": "0",
    "levelNum": "2",
    "standard": "1",
    "enabled": "1",
    "setYear": "2021",
    "operateDate": "Dec 25, 2019 8:46:30 PM",
    "path": "广东省 江门市",
    "province": "广东省 ",
    "localCity": "江门市",
    "children": [
      {
        "id": "2194",
        "regionCode": "440703",
        "name": "江门市市本级",
        "parentId": "2193",
        "leaf": "1",
        "levelNum": "3",
        "standard": "1",
        "enabled": "1",
        "setYear": "2021",
        "operateDate": "Dec 25, 2019 8:46:30 PM",
        "path": "广东省 江门市 市本级",
        "province": "广东省 ",
        "localCity": "江门市 "
      },
      {
        "id": "2195",
        "regionCode": "440703",
        "name": "蓬江区",
        "parentId": "2193",
        "leaf": "1",
        "levelNum": "3",
        "standard": "1",
        "enabled": "1",
        "setYear": "2021",
        "operateDate": "Dec 25, 2019 8:46:30 PM",
        "path": "广东省 江门市 蓬江区",
        "province": "广东省 ",
        "localCity": "江门市 "
      },{
        "id": "2196",
        "regionCode": "440704",
        "name": "江海区",
        "parentId": "2193",
        "leaf": "1",
        "levelNum": "3",
        "standard": "1",
        "enabled": "1",
        "setYear": "2021",
        "operateDate": "Dec 25, 2019 8:46:30 PM",
        "path": "广东省 江门市 江海区",
        "province": "广东省 ",
        "localCity": "江门市 "
      },{
        "id": "2197",
        "regionCode": "440705",
        "name": "新会区",
        "parentId": "2193",
        "leaf": "1",
        "levelNum": "3",
        "standard": "1",
        "enabled": "1",
        "setYear": "2021",
        "operateDate": "Dec 25, 2019 8:46:30 PM",
        "path": "广东省 江门市 新会区",
        "province": "广东省 ",
        "localCity": "江门市 "
      },
      {
        "id": "2200",
        "regionCode": "440784",
        "name": "鹤山市",
        "parentId": "2193",
        "leaf": "1",
        "levelNum": "3",
        "standard": "1",
        "enabled": "1",
        "setYear": "2021",
        "operateDate": "Dec 25, 2019 8:46:30 PM",
        "path": "广东省 江门市 鹤山市",
        "province": "广东省 ",
        "localCity": "江门市 "
      },{
        "id": "2198",
        "regionCode": "440781",
        "name": "台山市",
        "parentId": "2193",
        "leaf": "1",
        "levelNum": "3",
        "standard": "1",
        "enabled": "1",
        "setYear": "2021",
        "operateDate": "Dec 25, 2019 8:46:30 PM",
        "path": "广东省 江门市 台山市",
        "province": "广东省 ",
        "localCity": "江门市 "
      },{
        "id": "2201",
        "regionCode": "440785",
        "name": "恩平市",
        "parentId": "2193",
        "leaf": "1",
        "levelNum": "3",
        "standard": "1",
        "enabled": "1",
        "setYear": "2021",
        "operateDate": "Dec 25, 2019 8:46:30 PM",
        "path": "广东省 江门市 恩平市",
        "province": "广东省 ",
        "localCity": "江门市 "
      },
      {
        "id": "2199",
        "regionCode": "440783",
        "name": "开平市",
        "parentId": "2193",
        "leaf": "1",
        "levelNum": "3",
        "standard": "1",
        "enabled": "1",
        "setYear": "2021",
        "operateDate": "Dec 25, 2019 8:46:30 PM",
        "path": "广东省 江门市 开平市",
        "province": "广东省 ",
        "localCity": "江门市 "
      }

    ]
  },
  {
    "id": "2262",
    "regionCode": "441701",
    "name": "阳江市",
    "parentId": "2137",
    "leaf": "0",
    "levelNum": "2",
    "standard": "1",
    "enabled": "1",
    "setYear": "2021",
    "operateDate": "Dec 25, 2019 8:46:30 PM",
    "path": "广东省 阳江市",
    "province": "广东省 ",
    "localCity": "阳江市",
    "children": [
      {
        "id": "2263",
        "regionCode": "441701",
        "name": "阳江市市本级",
        "parentId": "2262",
        "leaf": "1",
        "levelNum": "3",
        "standard": "1",
        "enabled": "1",
        "setYear": "2021",
        "operateDate": "Dec 25, 2019 8:46:30 PM",
        "path": "广东省 阳江市 市本级",
        "province": "广东省 ",
        "localCity": "阳江市 "
      },
      {
        "id": "2267",
        "regionCode": "441781",
        "name": "阳春市",
        "parentId": "2262",
        "leaf": "1",
        "levelNum": "3",
        "standard": "1",
        "enabled": "1",
        "setYear": "2021",
        "operateDate": "Dec 25, 2019 8:46:30 PM",
        "path": "广东省 阳江市 阳春市",
        "province": "广东省 ",
        "localCity": "阳江市 "
      },{
        "id": "2265",
        "regionCode": "441721",
        "name": "阳西县",
        "parentId": "2262",
        "leaf": "1",
        "levelNum": "3",
        "standard": "1",
        "enabled": "1",
        "setYear": "2021",
        "operateDate": "Dec 25, 2019 8:46:30 PM",
        "path": "广东省 阳江市 阳西县",
        "province": "广东省 ",
        "localCity": "阳江市 "
      },{
        "id": "2266",
        "regionCode": "441723",
        "name": "阳东区",
        "parentId": "2262",
        "leaf": "1",
        "levelNum": "3",
        "standard": "1",
        "enabled": "1",
        "setYear": "2021",
        "operateDate": "Dec 25, 2019 8:46:30 PM",
        "path": "广东省 阳江市 阳东县",
        "province": "广东省 ",
        "localCity": "阳江市 "
      },{
        "id": "2264",
        "regionCode": "441702",
        "name": "江城区",
        "parentId": "2262",
        "leaf": "1",
        "levelNum": "3",
        "standard": "1",
        "enabled": "1",
        "setYear": "2021",
        "operateDate": "Dec 25, 2019 8:46:30 PM",
        "path": "广东省 阳江市 江城区",
        "province": "广东省 ",
        "localCity": "阳江市 "
      },
      {
        "id": "c635a57c-49b1-11eb-b35f-fa163e098fbb",
        "regionCode": "441705000",
        "name": "海陵岛经济开发试验区 ",
        "parentId": "2262",
        "leaf": "1",
        "levelNum": "3",
        "standard": "1",
        "enabled": "1",
        "setYear": "2021",
        "operateDate": "Dec 29, 2020 4:42:24 PM",
        "path": "广东省 阳江市 海陵岛经济开发试验区",
        "province": "广东省 ",
        "localCity": "阳江市"
      },
      {
        "id": "37C92C470F39404E892F599E65C5ED0E",
        "regionCode": "441743",
        "name": "阳江高新技术产业开发区",
        "parentId": "2262",
        "leaf": "1",
        "remark": "2020-2区划",
        "levelNum": "3",
        "standard": "1",
        "enabled": "1",
        "setYear": "2021",
        "operateDate": "Jun 5, 2020 10:32:01 AM"
      },
      {
        "id": "c63cd46b-49b1-11eb-b35f-fa163e098fbb",
        "regionCode": "441707000",
        "name": "阳江滨海新区 ",
        "parentId": "2262",
        "leaf": "1",
        "levelNum": "3",
        "standard": "1",
        "enabled": "1",
        "setYear": "2021",
        "operateDate": "Dec 29, 2020 4:42:24 PM",
        "path": "广东省 阳江市 阳江滨海新区",
        "province": "广东省 ",
        "localCity": "阳江市"
      }
    ]
  },
  {
    "id": "2202",
    "regionCode": "440801",
    "name": "湛江市",
    "parentId": "2137",
    "leaf": "0",
    "levelNum": "2",
    "standard": "1",
    "enabled": "1",
    "setYear": "2021",
    "operateDate": "Dec 25, 2019 8:46:30 PM",
    "path": "广东省 湛江市",
    "province": "广东省 ",
    "localCity": "湛江市",
    "children": [
      {
        "id": "2203",
        "regionCode": "440802",
        "name": "湛江市市本级",
        "parentId": "2202",
        "leaf": "1",
        "levelNum": "3",
        "standard": "1",
        "enabled": "1",
        "setYear": "2021",
        "operateDate": "Dec 25, 2019 8:46:30 PM",
        "path": "广东省 湛江市 市本级",
        "province": "广东省 ",
        "localCity": "湛江市 "
      },
      {
        "id": "2204",
        "regionCode": "440802",
        "name": "赤坎区",
        "parentId": "2202",
        "leaf": "1",
        "levelNum": "3",
        "standard": "1",
        "enabled": "1",
        "setYear": "2021",
        "operateDate": "Dec 25, 2019 8:46:30 PM",
        "path": "广东省 湛江市 赤坎区",
        "province": "广东省 ",
        "localCity": "湛江市 "
      },
      {
        "id": "2205",
        "regionCode": "440803",
        "name": "霞山区",
        "parentId": "2202",
        "leaf": "1",
        "levelNum": "3",
        "standard": "1",
        "enabled": "1",
        "setYear": "2021",
        "operateDate": "Dec 25, 2019 8:46:30 PM",
        "path": "广东省 湛江市 霞山区",
        "province": "广东省 ",
        "localCity": "湛江市 "
      },
      {
        "id": "2207",
        "regionCode": "440811",
        "name": "麻章区",
        "parentId": "2202",
        "leaf": "1",
        "levelNum": "3",
        "standard": "1",
        "enabled": "1",
        "setYear": "2021",
        "operateDate": "Dec 25, 2019 8:46:30 PM",
        "path": "广东省 湛江市 麻章区",
        "province": "广东省 ",
        "localCity": "湛江市 "
      },
      {
        "id": "2206",
        "regionCode": "440804",
        "name": "坡头区",
        "parentId": "2202",
        "leaf": "1",
        "levelNum": "3",
        "standard": "1",
        "enabled": "1",
        "setYear": "2021",
        "operateDate": "Dec 25, 2019 8:46:30 PM",
        "path": "广东省 湛江市 坡头区",
        "province": "广东省 ",
        "localCity": "湛江市 "
      },
      {
        "id": "2211",
        "regionCode": "440882",
        "name": "雷州市",
        "parentId": "2202",
        "leaf": "1",
        "levelNum": "3",
        "standard": "1",
        "enabled": "1",
        "setYear": "2021",
        "operateDate": "Dec 25, 2019 8:46:30 PM",
        "path": "广东省 湛江市 雷州市",
        "province": "广东省 ",
        "localCity": "湛江市 "
      },
      {
        "id": "2210",
        "regionCode": "440881",
        "name": "廉江市",
        "parentId": "2202",
        "leaf": "1",
        "levelNum": "3",
        "standard": "1",
        "enabled": "1",
        "setYear": "2021",
        "operateDate": "Dec 25, 2019 8:46:30 PM",
        "path": "广东省 湛江市 廉江市",
        "province": "广东省 ",
        "localCity": "湛江市 "
      },
      {
        "id": "2212",
        "regionCode": "440883",
        "name": "吴川市",
        "parentId": "2202",
        "leaf": "1",
        "levelNum": "3",
        "standard": "1",
        "enabled": "1",
        "setYear": "2021",
        "operateDate": "Dec 25, 2019 8:46:30 PM",
        "path": "广东省 湛江市 吴川市",
        "province": "广东省 ",
        "localCity": "湛江市 "
      },
      {
        "id": "2208",
        "regionCode": "440823",
        "name": "遂溪县",
        "parentId": "2202",
        "leaf": "1",
        "levelNum": "3",
        "standard": "1",
        "enabled": "1",
        "setYear": "2021",
        "operateDate": "Dec 25, 2019 8:46:30 PM",
        "path": "广东省 湛江市 遂溪县",
        "province": "广东省 ",
        "localCity": "湛江市 "
      },
      {
        "id": "2209",
        "regionCode": "440825",
        "name": "徐闻县",
        "parentId": "2202",
        "leaf": "1",
        "levelNum": "3",
        "standard": "1",
        "enabled": "1",
        "setYear": "2021",
        "operateDate": "Dec 25, 2019 8:46:30 PM",
        "path": "广东省 湛江市 徐闻县",
        "province": "广东省 ",
        "localCity": "湛江市 "
      },
      {
        "id": "B8FA47362A844033AC344EC6763D244F",
        "regionCode": "440840",
        "name": "湛江经济技术开发区管委会",
        "parentId": "2202",
        "leaf": "1",
        "remark": "2020-2区划",
        "levelNum": "3",
        "standard": "1",
        "enabled": "1",
        "setYear": "2021",
        "operateDate": "Jun 5, 2020 10:19:09 AM"
      }
    ]
  },
  {
    "id": "2213",
    "regionCode": "440901",
    "name": "茂名市",
    "parentId": "2137",
    "leaf": "0",
    "levelNum": "2",
    "standard": "1",
    "enabled": "1",
    "setYear": "2021",
    "operateDate": "Dec 25, 2019 8:46:30 PM",
    "path": "广东省 茂名市",
    "province": "广东省 ",
    "localCity": "茂名市",
    "children": [
      {
        "id": "2214",
        "regionCode": "440901",
        "name": "茂名市市本级",
        "parentId": "2213",
        "leaf": "1",
        "levelNum": "3",
        "standard": "1",
        "enabled": "1",
        "setYear": "2021",
        "operateDate": "Dec 25, 2019 8:46:30 PM",
        "path": "广东省 茂名市 市本级",
        "province": "广东省 ",
        "localCity": "茂名市 "
      },
      {
        "id": "2215",
        "regionCode": "440902",
        "name": "茂南区",
        "parentId": "2213",
        "leaf": "1",
        "levelNum": "3",
        "standard": "1",
        "enabled": "1",
        "setYear": "2021",
        "operateDate": "Dec 25, 2019 8:46:30 PM",
        "path": "广东省 茂名市 茂南区",
        "province": "广东省 ",
        "localCity": "茂名市 "
      },{
        "id": "2218",
        "regionCode": "440981",
        "name": "高州市",
        "parentId": "2213",
        "leaf": "1",
        "levelNum": "3",
        "standard": "1",
        "enabled": "1",
        "setYear": "2021",
        "operateDate": "Dec 25, 2019 8:46:30 PM",
        "path": "广东省 茂名市 高州市",
        "province": "广东省 ",
        "localCity": "茂名市 "
      },{
        "id": "2220",
        "regionCode": "440983",
        "name": "信宜市",
        "parentId": "2213",
        "leaf": "1",
        "levelNum": "3",
        "standard": "1",
        "enabled": "1",
        "setYear": "2021",
        "operateDate": "Dec 25, 2019 8:46:30 PM",
        "path": "广东省 茂名市 信宜市",
        "province": "广东省 ",
        "localCity": "茂名市 "
      },{
        "id": "2219",
        "regionCode": "440982",
        "name": "化州市",
        "parentId": "2213",
        "leaf": "1",
        "levelNum": "3",
        "standard": "1",
        "enabled": "1",
        "setYear": "2021",
        "operateDate": "Dec 25, 2019 8:46:30 PM",
        "path": "广东省 茂名市 化州市",
        "province": "广东省 ",
        "localCity": "茂名市 "
      },
      {
        "id": "3FE6CE31B87947D4A62FC0C5BFF0CDB7",
        "regionCode": "440904",
        "name": "电白区",
        "parentId": "2213",
        "leaf": "1",
        "remark": "2020-2区划",
        "levelNum": "3",
        "standard": "1",
        "enabled": "1",
        "setYear": "2021",
        "operateDate": "Jun 5, 2020 10:20:34 AM"
      },
      {
        "id": "CE5214A0B2F248D2925465900121A4BE",
        "regionCode": "440941",
        "name": "高新技术产业开发区",
        "parentId": "2213",
        "leaf": "1",
        "remark": "2020-2区划",
        "levelNum": "3",
        "standard": "1",
        "enabled": "1",
        "setYear": "2021",
        "operateDate": "Jun 5, 2020 10:21:11 AM"
      },


      {
        "id": "08856A6F96E24A51AA56C8AE6245E54A",
        "regionCode": "440940",
        "name": "滨海新区",
        "parentId": "2213",
        "leaf": "1",
        "remark": "2020-2区划",
        "levelNum": "3",
        "standard": "1",
        "enabled": "1",
        "setYear": "2021",
        "operateDate": "Jun 5, 2020 10:20:52 AM"
      },

      {
        "id": "c64044f6-49b1-11eb-b35f-fa163e098fbb",
        "regionCode": "440904004",
        "name": "水东湾新城",
        "parentId": "2213",
        "leaf": "1",
        "levelNum": "3",
        "standard": "1",
        "enabled": "1",
        "setYear": "2021",
        "operateDate": "Dec 29, 2020 4:42:24 PM",
        "path": "广东省 茂名市 水东湾新城",
        "province": "广东省 ",
        "localCity": "茂名市"
      }
    ]
  },
  {
    "id": "2221",
    "regionCode": "441201",
    "name": "肇庆市",
    "parentId": "2137",
    "leaf": "0",
    "levelNum": "2",
    "standard": "1",
    "enabled": "1",
    "setYear": "2021",
    "operateDate": "Dec 25, 2019 8:46:30 PM",
    "path": "广东省 肇庆市",
    "province": "广东省 ",
    "localCity": "肇庆市",
    "children": [
      {
        "id": "2222",
        "regionCode": "441201",
        "name": "肇庆市市本级",
        "parentId": "2221",
        "leaf": "1",
        "levelNum": "3",
        "standard": "1",
        "enabled": "1",
        "setYear": "2021",
        "operateDate": "Dec 25, 2019 8:46:30 PM",
        "path": "广东省 肇庆市 市本级",
        "province": "广东省 ",
        "localCity": "肇庆市 "
      },
      {
        "id": "2223",
        "regionCode": "441202",
        "name": "端州区",
        "parentId": "2221",
        "leaf": "1",
        "levelNum": "3",
        "standard": "1",
        "enabled": "1",
        "setYear": "2021",
        "operateDate": "Dec 25, 2019 8:46:30 PM",
        "path": "广东省 肇庆市 端州区",
        "province": "广东省 ",
        "localCity": "肇庆市 "
      },
      {
        "id": "2224",
        "regionCode": "441203",
        "name": "鼎湖区",
        "parentId": "2221",
        "leaf": "1",
        "levelNum": "3",
        "standard": "1",
        "enabled": "1",
        "setYear": "2021",
        "operateDate": "Dec 25, 2019 8:46:30 PM",
        "path": "广东省 肇庆市 鼎湖区",
        "province": "广东省 ",
        "localCity": "肇庆市 "
      },
      {
        "id": "2229",
        "regionCode": "441283",
        "name": "高要区",
        "parentId": "2221",
        "leaf": "1",
        "levelNum": "3",
        "standard": "1",
        "enabled": "1",
        "setYear": "2021",
        "operateDate": "Dec 25, 2019 8:46:30 PM",
        "path": "广东省 肇庆市 高要区",
        "province": "广东省 ",
        "localCity": "肇庆市 "
      },
      {
        "id": "2230",
        "regionCode": "441284",
        "name": "四会市",
        "parentId": "2221",
        "leaf": "1",
        "levelNum": "3",
        "standard": "1",
        "enabled": "1",
        "setYear": "2021",
        "operateDate": "Dec 25, 2019 8:46:30 PM",
        "path": "广东省 肇庆市 四会市",
        "province": "广东省 ",
        "localCity": "肇庆市 "
      },
      {
        "id": "2225",
        "regionCode": "441223",
        "name": "广宁县",
        "parentId": "2221",
        "leaf": "1",
        "levelNum": "3",
        "standard": "1",
        "enabled": "1",
        "setYear": "2021",
        "operateDate": "Dec 25, 2019 8:46:30 PM",
        "path": "广东省 肇庆市 广宁县",
        "province": "广东省 ",
        "localCity": "肇庆市 "
      },
      {
        "id": "2228",
        "regionCode": "441226",
        "name": "德庆县",
        "parentId": "2221",
        "leaf": "1",
        "levelNum": "3",
        "standard": "1",
        "enabled": "1",
        "setYear": "2021",
        "operateDate": "Dec 25, 2019 8:46:30 PM",
        "path": "广东省 肇庆市 德庆县",
        "province": "广东省 ",
        "localCity": "肇庆市 "
      },
      {
        "id": "2227",
        "regionCode": "441225",
        "name": "封开县",
        "parentId": "2221",
        "leaf": "1",
        "levelNum": "3",
        "standard": "1",
        "enabled": "1",
        "setYear": "2021",
        "operateDate": "Dec 25, 2019 8:46:30 PM",
        "path": "广东省 肇庆市 封开县",
        "province": "广东省 ",
        "localCity": "肇庆市 "
      },
      {
        "id": "2226",
        "regionCode": "441224",
        "name": "怀集县",
        "parentId": "2221",
        "leaf": "1",
        "levelNum": "3",
        "standard": "1",
        "enabled": "1",
        "setYear": "2021",
        "operateDate": "Dec 25, 2019 8:46:30 PM",
        "path": "广东省 肇庆市 怀集县",
        "province": "广东省 ",
        "localCity": "肇庆市 "
      },
      {
        "id": "B04696F724C14D7B84E5AA56F24F5715",
        "regionCode": "441240",
        "name": "肇庆高新区",
        "parentId": "2221",
        "leaf": "1",
        "remark": "2020-2区划",
        "levelNum": "3",
        "standard": "1",
        "enabled": "1",
        "setYear": "2021",
        "operateDate": "Jun 5, 2020 10:21:55 AM"
      },
      {
        "id": "c63ea8d1-49b1-11eb-b35f-fa163e098fbb",
        "regionCode": "441206000",
        "name": "肇庆新区",
        "parentId": "2221",
        "leaf": "1",
        "levelNum": "3",
        "standard": "1",
        "enabled": "1",
        "setYear": "2021",
        "operateDate": "Dec 29, 2020 4:42:24 PM",
        "path": "广东省 肇庆市 肇庆新区",
        "province": "广东省 ",
        "localCity": "肇庆市"
      },
      {
        "id": "73001334-aabf-4cac-95c2-c6ae2005cbeb",
        "regionCode": "441206001",
        "name": "粤桂合作特别试验区",
        "parentId": "2221",
        "leaf": "1",
        "levelNum": "3",
        "standard": "1",
        "enabled": "1",
        "setYear": "2021",
        "operateDate": "Dec 29, 2020 4:42:24 PM",
        "path": "广东省 肇庆市 粤桂合作特别试验区",
        "province": "广东省 ",
        "localCity": "肇庆市"
      }
    ]
  },
  {
    "id": "2268",
    "regionCode": "441801",
    "name": "清远市",
    "parentId": "2137",
    "leaf": "0",
    "levelNum": "2",
    "standard": "1",
    "enabled": "1",
    "setYear": "2021",
    "operateDate": "Dec 25, 2019 8:46:30 PM",
    "path": "广东省 清远市",
    "province": "广东省 ",
    "localCity": "清远市",
    "children": [
      {
        "id": "2269",
        "regionCode": "441801",
        "name": "清远市市本级",
        "parentId": "2268",
        "leaf": "1",
        "levelNum": "3",
        "standard": "1",
        "enabled": "1",
        "setYear": "2021",
        "operateDate": "Dec 25, 2019 8:46:30 PM",
        "path": "广东省 清远市 市本级",
        "province": "广东省 ",
        "localCity": "清远市 "
      },
      {
        "id": "D3EF258BC0474A828E16060FDE1EEC88",
        "regionCode": "441804",
        "name": "清远高新区",
        "parentId": "2268",
        "leaf": "1",
        "levelNum": "3",
        "standard": "1",
        "enabled": "1",
        "setYear": "2021",
        "operateDate": "Jan 14, 2021 8:12:44 PM"
      },{
        "id": "2270",
        "regionCode": "441802",
        "name": "清城区",
        "parentId": "2268",
        "leaf": "1",
        "levelNum": "3",
        "standard": "1",
        "enabled": "1",
        "setYear": "2021",
        "operateDate": "Dec 25, 2019 8:46:30 PM",
        "path": "广东省 清远市 清城区",
        "province": "广东省 ",
        "localCity": "清远市 "
      },{
        "id": "419D0C944315471E830102B695635A13",
        "regionCode": "441803",
        "name": "清新区",
        "parentId": "2268",
        "leaf": "1",
        "remark": "2020-2区划",
        "levelNum": "3",
        "standard": "1",
        "enabled": "1",
        "setYear": "2021",
        "operateDate": "Jun 5, 2020 10:33:45 AM"
      },{
        "id": "2276",
        "regionCode": "441881",
        "name": "英德市",
        "parentId": "2268",
        "leaf": "1",
        "levelNum": "3",
        "standard": "1",
        "enabled": "1",
        "setYear": "2021",
        "operateDate": "Dec 25, 2019 8:46:30 PM",
        "path": "广东省 清远市 英德市",
        "province": "广东省 ",
        "localCity": "清远市 "
      },{
        "id": "2277",
        "regionCode": "441882",
        "name": "连州市",
        "parentId": "2268",
        "leaf": "1",
        "levelNum": "3",
        "standard": "1",
        "enabled": "1",
        "setYear": "2021",
        "operateDate": "Dec 25, 2019 8:46:30 PM",
        "path": "广东省 清远市 连州市",
        "province": "广东省 ",
        "localCity": "清远市 "
      },{
        "id": "2271",
        "regionCode": "441821",
        "name": "佛冈县",
        "parentId": "2268",
        "leaf": "1",
        "levelNum": "3",
        "standard": "1",
        "enabled": "1",
        "setYear": "2021",
        "operateDate": "Dec 25, 2019 8:46:30 PM",
        "path": "广东省 清远市 佛冈县",
        "province": "广东省 ",
        "localCity": "清远市 "
      },{
        "id": "2273",
        "regionCode": "441825",
        "name": "连山壮族瑶族自治县",
        "parentId": "2268",
        "leaf": "1",
        "levelNum": "3",
        "standard": "1",
        "enabled": "1",
        "setYear": "2021",
        "operateDate": "Dec 25, 2019 8:46:30 PM",
        "path": "广东省 清远市 连山壮族瑶族自治县",
        "province": "广东省 ",
        "localCity": "清远市 "
      },
      {
        "id": "2274",
        "regionCode": "441826",
        "name": "连南瑶族自治区",
        "parentId": "2268",
        "leaf": "1",
        "levelNum": "3",
        "standard": "1",
        "enabled": "1",
        "setYear": "2021",
        "operateDate": "Dec 25, 2019 8:46:30 PM",
        "path": "广东省 清远市 连南瑶族自治区",
        "province": "广东省 ",
        "localCity": "清远市 "
      },{
        "id": "2272",
        "regionCode": "441823",
        "name": "阳山县",
        "parentId": "2268",
        "leaf": "1",
        "levelNum": "3",
        "standard": "1",
        "enabled": "1",
        "setYear": "2021",
        "operateDate": "Dec 25, 2019 8:46:30 PM",
        "path": "广东省 清远市 阳山县",
        "province": "广东省 ",
        "localCity": "清远市 "
      },
      {
        "id": "19DAD52A63F54419B719E05F0D7D3D4E",
        "regionCode": "441805",
        "name": "广清产业园",
        "parentId": "2268",
        "leaf": "1",
        "levelNum": "3",
        "standard": "1",
        "enabled": "1",
        "setYear": "2021",
        "operateDate": "Jan 14, 2021 8:14:28 PM"
      }

    ]
  },
  {
    "id": "2280",
    "regionCode": "445101",
    "name": "潮州市",
    "parentId": "2137",
    "leaf": "0",
    "levelNum": "2",
    "standard": "1",
    "enabled": "1",
    "setYear": "2021",
    "operateDate": "Dec 25, 2019 8:46:30 PM",
    "path": "广东省 潮州市",
    "province": "广东省 ",
    "localCity": "潮州市",
    "children": [
      {
        "id": "2281",
        "regionCode": "445101",
        "name": "潮州市市本级",
        "parentId": "2280",
        "leaf": "1",
        "levelNum": "3",
        "standard": "1",
        "enabled": "1",
        "setYear": "2021",
        "operateDate": "Dec 25, 2019 8:46:30 PM",
        "path": "广东省 潮州市 市本级",
        "province": "广东省 ",
        "localCity": "潮州市 "
      },
      {
        "id": "2283",
        "regionCode": "445103",
        "name": "潮安区",
        "parentId": "2280",
        "leaf": "1",
        "levelNum": "3",
        "standard": "1",
        "enabled": "1",
        "setYear": "2021",
        "operateDate": "Dec 25, 2019 8:46:30 PM",
        "path": "广东省 潮州市 潮安区",
        "province": "广东省 ",
        "localCity": "潮州市 "
      },
      {
        "id": "2284",
        "regionCode": "445122",
        "name": "饶平县",
        "parentId": "2280",
        "leaf": "1",
        "levelNum": "3",
        "standard": "1",
        "enabled": "1",
        "setYear": "2021",
        "operateDate": "Dec 25, 2019 8:46:30 PM",
        "path": "广东省 潮州市 饶平县",
        "province": "广东省 ",
        "localCity": "潮州市 "
      },
      {
        "id": "2282",
        "regionCode": "445102",
        "name": "湘桥区",
        "parentId": "2280",
        "leaf": "1",
        "levelNum": "3",
        "standard": "1",
        "enabled": "1",
        "setYear": "2021",
        "operateDate": "Dec 25, 2019 8:46:30 PM",
        "path": "广东省 潮州市 湘桥区",
        "province": "广东省 ",
        "localCity": "潮州市 "
      },
      {
        "id": "EE83AAA4E93D46C0ADB66309434AF7E8",
        "regionCode": "445140",
        "name": "枫溪区",
        "parentId": "2280",
        "leaf": "1",
        "remark": "2020-2区划",
        "levelNum": "3",
        "standard": "1",
        "enabled": "1",
        "setYear": "2021",
        "operateDate": "Jun 5, 2020 10:35:25 AM"
      }
    ]
  },
  {
    "id": "2285",
    "regionCode": "445201",
    "name": "揭阳市",
    "parentId": "2137",
    "leaf": "0",
    "levelNum": "2",
    "standard": "1",
    "enabled": "1",
    "setYear": "2021",
    "operateDate": "Dec 25, 2019 8:46:30 PM",
    "path": "广东省 揭阳市",
    "province": "广东省 ",
    "localCity": "揭阳市",
    "children": [
      {
        "id": "2286",
        "regionCode": "445201",
        "name": "揭阳市市本级",
        "parentId": "2285",
        "leaf": "1",
        "levelNum": "3",
        "standard": "1",
        "enabled": "1",
        "setYear": "2021",
        "operateDate": "Dec 25, 2019 8:46:30 PM",
        "path": "广东省 揭阳市 市本级",
        "province": "广东省 ",
        "localCity": "揭阳市 "
      },
      {
        "id": "50D8F2722AE24E84B2C756EF25B062F5",
        "regionCode": "445241",
        "name": "揭阳高新技术产业开发区",
        "parentId": "2285",
        "leaf": "1",
        "remark": "2020-2区划",
        "levelNum": "3",
        "standard": "1",
        "enabled": "1",
        "setYear": "2021",
        "operateDate": "Jun 5, 2020 10:36:35 AM"
      },
      {
        "id": "2289",
        "regionCode": "445222",
        "name": "揭西县",
        "parentId": "2285",
        "leaf": "1",
        "levelNum": "3",
        "standard": "1",
        "enabled": "1",
        "setYear": "2021",
        "operateDate": "Dec 25, 2019 8:46:30 PM",
        "path": "广东省 揭阳市 揭西县",
        "province": "广东省 ",
        "localCity": "揭阳市 "
      },{
        "id": "2291",
        "regionCode": "445281",
        "name": "普宁市",
        "parentId": "2285",
        "leaf": "1",
        "levelNum": "3",
        "standard": "1",
        "enabled": "1",
        "setYear": "2021",
        "operateDate": "Dec 25, 2019 8:46:30 PM",
        "path": "广东省 揭阳市 普宁市",
        "province": "广东省 ",
        "localCity": "揭阳市 "
      },{
        "id": "94E25B828A4F475998E211D91DE2FC7E",
        "regionCode": "445246",
        "name": "大南海工业区",
        "parentId": "2285",
        "leaf": "1",
        "remark": "2020-2区划",
        "levelNum": "3",
        "standard": "1",
        "enabled": "1",
        "setYear": "2021",
        "operateDate": "Jun 5, 2020 10:37:48 AM"
      },
      {
        "id": "33B05623756E4996B837A1E36683614E",
        "regionCode": "445240",
        "name": "揭阳产业转移工业园",
        "parentId": "2285",
        "leaf": "1",
        "remark": "2020-2区划",
        "levelNum": "3",
        "standard": "1",
        "enabled": "1",
        "setYear": "2021",
        "operateDate": "Jun 5, 2020 10:37:20 AM"
      },{
        "id": "054A3E46B59D46B0AB4ABDEEFF0AD29E",
        "regionCode": "445203",
        "name": "揭东区",
        "parentId": "2285",
        "leaf": "1",
        "remark": "2020-2区划",
        "levelNum": "3",
        "standard": "1",
        "enabled": "1",
        "setYear": "2021",
        "operateDate": "Jun 5, 2020 10:35:55 AM"
      },{
        "id": "2287",
        "regionCode": "445202",
        "name": "榕城区",
        "parentId": "2285",
        "leaf": "1",
        "levelNum": "3",
        "standard": "1",
        "enabled": "1",
        "setYear": "2021",
        "operateDate": "Dec 25, 2019 8:46:30 PM",
        "path": "广东省 揭阳市 榕城区",
        "province": "广东省 ",
        "localCity": "揭阳市 "
      },{
        "id": "2290",
        "regionCode": "445224",
        "name": "惠来县",
        "parentId": "2285",
        "leaf": "1",
        "levelNum": "3",
        "standard": "1",
        "enabled": "1",
        "setYear": "2021",
        "operateDate": "Dec 25, 2019 8:46:30 PM",
        "path": "广东省 揭阳市 惠来县",
        "province": "广东省 ",
        "localCity": "揭阳市 "
      },{
        "id": "1cfa07e6-49c5-11eb-b35f-fa163e098fbb",
        "regionCode": "445224099",
        "name": "粤东新城",
        "parentId": "2285",
        "leaf": "1",
        "levelNum": "3",
        "standard": "1",
        "enabled": "1",
        "setYear": "2021",
        "operateDate": "Dec 29, 2020 7:00:50 PM",
        "path": "广东省 揭阳市 粤东新城",
        "province": "广东省",
        "localCity": "揭阳市"
      }
    ]
  },
  {
    "id": "2292",
    "regionCode": "445301",
    "name": "云浮市",
    "parentId": "2137",
    "leaf": "0",
    "levelNum": "2",
    "standard": "1",
    "enabled": "1",
    "setYear": "2021",
    "operateDate": "Dec 25, 2019 8:46:30 PM",
    "path": "广东省 云浮市",
    "province": "广东省 ",
    "localCity": "云浮市",
    "children": [
      {
        "id": "2293",
        "regionCode": "445301",
        "name": "云浮市市本级",
        "parentId": "2292",
        "leaf": "1",
        "levelNum": "3",
        "standard": "1",
        "enabled": "1",
        "setYear": "2021",
        "operateDate": "Dec 25, 2019 8:46:30 PM",
        "path": "广东省 云浮市 市本级",
        "province": "广东省 ",
        "localCity": "云浮市 "
      },
      {
        "id": "2294",
        "regionCode": "445302",
        "name": "云城区",
        "parentId": "2292",
        "leaf": "1",
        "levelNum": "3",
        "standard": "1",
        "enabled": "1",
        "setYear": "2021",
        "operateDate": "Dec 25, 2019 8:46:30 PM",
        "path": "广东省 云浮市 云城区",
        "province": "广东省 ",
        "localCity": "云浮市 "
      },
      {
        "id": "32FD3FED4CC44417A5289941EBE948A2",
        "regionCode": "445303",
        "name": "云安区",
        "parentId": "2292",
        "leaf": "1",
        "remark": "2020-2区划",
        "levelNum": "3",
        "standard": "1",
        "enabled": "1",
        "setYear": "2021",
        "operateDate": "Jun 5, 2020 10:38:26 AM"
      },
      {
        "id": "2298",
        "regionCode": "445381",
        "name": "罗定市",
        "parentId": "2292",
        "leaf": "1",
        "levelNum": "3",
        "standard": "1",
        "enabled": "1",
        "setYear": "2021",
        "operateDate": "Dec 25, 2019 8:46:30 PM",
        "path": "广东省 云浮市 罗定市",
        "province": "广东省 ",
        "localCity": "云浮市 "
      },
      {
        "id": "2295",
        "regionCode": "445321",
        "name": "新兴县",
        "parentId": "2292",
        "leaf": "1",
        "levelNum": "3",
        "standard": "1",
        "enabled": "1",
        "setYear": "2021",
        "operateDate": "Dec 25, 2019 8:46:30 PM",
        "path": "广东省 云浮市 新兴县",
        "province": "广东省 ",
        "localCity": "云浮市 "
      },
      {
        "id": "2296",
        "regionCode": "445322",
        "name": "郁南县",
        "parentId": "2292",
        "leaf": "1",
        "levelNum": "3",
        "standard": "1",
        "enabled": "1",
        "setYear": "2021",
        "operateDate": "Dec 25, 2019 8:46:30 PM",
        "path": "广东省 云浮市 郁南县",
        "province": "广东省 ",
        "localCity": "云浮市 "
      },
      {
        "id": "2297",
        "regionCode": "445304000",
        "name": "云浮新区",
        "parentId": "2292",
        "leaf": "1",
        "levelNum": "3",
        "standard": "1",
        "enabled": "1",
        "setYear": "2021",
        "operateDate": "Dec 25, 2019 8:46:30 PM",
        "path": "广东省 云浮市 云浮新区",
        "province": "广东省 ",
        "localCity": "云浮市 "
      }
    ]
  },
  {
    "id": "E322534E494A48E6AAF1470631B21DD5",
    "regionCode": "440442",
    "name": "横琴粤澳深度合作区",
    "parentId": "2137",
    "leaf": "0",
    "levelNum": "2",
    "standard": "1",
    "enabled": "1",
    "setYear": "2021",
    "operateDate": "Jun 5, 2020 10:17:05 AM",
    "path": "广东省 横琴粤澳深度合作区",
    "province": "广东省 ",
    "localCity": "横琴粤澳深度合作区"
  }
]