{"code":"0","data":{"overDate":"2022-12-01","note":null,"addTime":null,"proofOrSerialCode":"2019-441900-34-03-011678","submitDate":"2019/03/14 14:16:55","fullName":"东莞市常平镇经济发展局","updateTime":"2022/09/27 09:16:46","expiryDate":"2022-03-26","applyOrgan":"东莞市伟创华鑫自动化设备有限公司","beginDate":"2021-06-01","hasStart":0,"sfjz":"0","scope":"通过建设本项目形成年产3万套智能机械式立体停车设备的生产能力。本项目总投资21400万元，其中设备购置及安装14800万元，工程建设及其它费用6600万元。","finishDate":"2019-03-19","id":"e06d7ecf-73ae-11ec-9ad9-fa164ee08b71","place":"东莞市常平镇","stateFlagName":"办结（通过）","projectName":"智能机械式立体停车设备制造项目","totalInvest":21400.0000,"isValidity":"有效"},"message":"查询成功！","status":200}