{"code":"0","data":{"overDate":"2022-10-01","note":null,"addTime":null,"proofOrSerialCode":"2020-441900-39-03-039107","submitDate":"2020/05/19 11:10:57","fullName":"东莞市松山湖产业发展局","updateTime":"2022/09/27 09:16:46","expiryDate":"2022/05/19 15:52:52","applyOrgan":"广东丹邦科技有限公司","beginDate":"2020-10-01","hasStart":0,"sfjz":"0","scope":"投资总额为181,757.73万元，引进国内外先进设备建设一条量子碳化合物厚膜生产线、一条新型透明PI膜中试生产线、一条量子碳化合物半导体膜研发试验线。项目达产后年产100万平方米量子碳化合物厚膜、30万平方新型透明PI膜。 建筑面积：23650平方米、占地面积：10021平方米。 ","finishDate":"2020-05-19","id":"e1b110a7-73ae-11ec-9ad9-fa164ee08b71","place":"东莞市松山湖工业西一路广东丹邦工业园","stateFlagName":"办结（通过）","projectName":"丹邦科技松山湖增资扩产项目","totalInvest":181758.6200,"isValidity":"有效"},"message":"查询成功！","status":200}