{"code":"0","data":{"overDate":"2026-02-01","note":null,"addTime":null,"proofOrSerialCode":"2020-441900-72-03-106402","submitDate":"2020/11/24 09:14:26","fullName":"东莞市东坑镇工业信息科技局","updateTime":"2022/09/27 09:16:46","expiryDate":"2022/11/26 18:07:01","applyOrgan":"东莞市东坑平谦工业园开发有限公司","beginDate":"2021-03-01","hasStart":0,"sfjz":"0","scope":"东莞北斗智谷特色小镇总规划面积2平方公里，占地面积约为12万平方米，建筑面积约为12万平方米，总投资10亿元。主要建设内容为：北斗智谷、产业综合服务中心、小镇客厅、文化街区、数字经济配套产业区等。","finishDate":"2020-11-26","id":"e269c1cd-73ae-11ec-9ad9-fa164ee08b71","place":"东莞市东坑镇东坑平谦国际工业园","stateFlagName":"办结（通过）","projectName":"东莞北斗智谷工业区","totalInvest":100000.0000,"isValidity":"有效"},"message":"查询成功！","status":200}