{"code":"0","data":{"overDate":"2020-02-01","note":null,"addTime":null,"proofOrSerialCode":"2019-441900-52-03-079762","submitDate":"2019/12/03 10:12:53","fullName":"东莞市发展和改革局","updateTime":"2022/09/27 09:16:46","expiryDate":"2021/12/06 08:34:00","applyOrgan":"广东美华智充科技有限公司","beginDate":"2019-12-01","hasStart":1,"sfjz":"0","scope":"建筑面积65平方米，占地面积360平方米，变压器容量800KVA（新建），充电站总功率480KW。桩数4台。功率：120KW直流充电机/4台，充电机类型：双枪直流充电桩。满足8台电动汽车同时充电。对外开放。符合消防安全等充电设施安全运营要求的配套设施和系统。","finishDate":"2019-12-06","id":"e1346b51-73ae-11ec-9ad9-fa164ee08b71","place":"东莞市东城街道办东城市民休闲公园内停车场","stateFlagName":"办结（通过）","projectName":"美华智充石井充电站项目","totalInvest":70.0000,"isValidity":"有效"},"message":"查询成功！","status":200}