{"code":"0","data":{"overDate":"2023-10-01","note":null,"addTime":null,"proofOrSerialCode":"2212-441900-04-01-523296","submitDate":"2022/12/13 11:48:43","fullName":"东莞市桥头镇经济发展局","updateTime":"2022/12/14 10:18:03","expiryDate":"2024-12-14","applyOrgan":"宝利鑫新能源开发有限公司东莞桥头分公司","beginDate":"2023-03-01","hasStart":0,"sfjz":"0","scope":"在东莞市桥头镇东莞市日新传导科技有限公司厂房屋顶上建设约为0.6兆瓦分布式光伏发电项目（二期），拟安装600W的多晶硅光伏组件1000块，占用屋顶面积约5600平方米。项目所发电能自发自用、余电上网。","finishDate":"2022-12-14","id":"1602850362383925249","place":"东莞市桥头镇桥新西二路6号","stateFlagName":"办结（通过）","projectName":"宝利鑫东莞市日新传导科技有限公司600KWp分布式光伏发电项目（二期）","totalInvest":435.0000,"isValidity":"有效"},"message":"查询成功！","status":200}