{"code":"0","data":{"overDate":"2022-07-01","note":null,"addTime":null,"proofOrSerialCode":"2204-441900-04-01-924215","submitDate":"2022/03/30 17:52:36","fullName":"东莞市发展和改革局","updateTime":"2022/09/27 09:16:46","expiryDate":"2024/04/01 17:39:23","applyOrgan":"东莞星充新能源有限公司","beginDate":"2022-04-01","hasStart":0,"sfjz":"0","scope":"充电站建设共16台充电桩，32个车位，总功率2160KW功率：120KW直流充电桩12台，180KW直流充电桩4台；新建3台800kVA变压器容量2400KVA。建成后为各类电动汽车提供充电服务,对外开放。符合消防安全等充电设施安全运营要求的配套设施和系统","finishDate":"2022-04-01","id":"1509827754722385922","place":"东莞市南城街道蛤地公园二期停车场","stateFlagName":"办结（通过）","projectName":"东莞南城蛤地公园充电站项目","totalInvest":480.0000,"isValidity":"有效"},"message":"查询成功！","status":200}