{"code":"0","data":{"overDate":"2021-01-01","note":null,"addTime":null,"proofOrSerialCode":"2012-441900-04-01-286712","submitDate":"2020/11/30 09:32:23","fullName":"东莞市发展和改革局","updateTime":"2022/09/27 09:16:46","expiryDate":"2022/12/28 23:23:29","applyOrgan":"特斯拉汽车销售服务（深圳）有限公司","beginDate":"2020-11-01","hasStart":0,"sfjz":"0","scope":"凤岗天安数码城超级充电站，位于广东省东莞市长安镇德政中路222号，占地面积含车位约120平方米。共建设4台总控箱，单箱功率135kw，总功率540kW，各附带2个充电枪。对外开放。符合消防安全等充电设施安全运营要求的配套设施和系统。   ","finishDate":"2020-12-28","id":"e26f90cb-73ae-11ec-9ad9-fa164ee08b71","place":"东莞市长安镇德政中路222号","stateFlagName":"办结（通过）","projectName":"凤岗天安数码城超级充电站","totalInvest":160.0000,"isValidity":"有效"},"message":"查询成功！","status":200}