{"code":"0","data":{"overDate":"2023-04-01","note":null,"addTime":null,"proofOrSerialCode":"2211-441900-04-01-213626","submitDate":"2022/11/02 16:01:44","fullName":"东莞市中堂镇经济发展局","updateTime":"2023/02/23 09:51:17","expiryDate":"2024-11-02","applyOrgan":"东莞鑫铭新能源开发有限公司","beginDate":"2022-12-01","hasStart":0,"sfjz":"0","scope":"在东莞市华迅实业投资有限公司自建的厂房屋顶上建设第一期1.83MW分布式光伏发电项目，采用550W的单晶太阳能电池板3324块，占用屋顶面积约12009平方米（一期项目分别为一号厂房屋顶南侧的2482平方米，二号厂房屋顶南侧的1912平方米，三号厂房屋顶南侧的1912平方米，六号厂房屋顶南侧的1602平方米，七号厂房屋顶南侧的1829平方米，八号厂房屋顶南侧的2272平方米），平均每年发电量约182万千瓦时，产品技术及安装系统符合相关国家行业标准。","finishDate":"2022-11-02","id":"1587721536335278081","place":"东莞市中堂镇斗朗社区斗朗工业区","stateFlagName":"办结（通过）","projectName":"东莞市华迅实业投资有限公司1.83MW分布式光伏发电项目","totalInvest":727.0000,"isValidity":"有效"},"message":"查询成功！","status":200}