{"code":"0","data":{"overDate":"2022-07-01","note":null,"addTime":null,"proofOrSerialCode":"2020-441900-41-03-047644","submitDate":"2020/06/06 14:13:06","fullName":"东莞市茶山镇经济发展局","updateTime":"2022/09/27 09:16:46","expiryDate":"2022/06/12 16:31:30","applyOrgan":"广东宏强新型材料科技有限公司","beginDate":"2020-07-01","hasStart":0,"sfjz":"0","scope":"广东宏强新型材料科技有限公司拟投产口罩机（KN95）50台及熔喷无纺布机10台，口罩机产能约为75000个/天/台、熔喷无纺布机产能约1吨/天/台；投资金额约为1.2亿元用于固定资产投资计划；需土地约30000平方米、建筑面积约为45000平方米；投资金额来源为公司及股东自有资金。 ","finishDate":"2020-06-12","id":"e1c352de-73ae-11ec-9ad9-fa164ee08b71","place":"东莞市茶山镇刘黄工业二路17号401室","stateFlagName":"办结（通过）","projectName":"广东宏强新型材料科技有限公司关于口罩机及熔喷无纺布机项目投资","totalInvest":12000.0000,"isValidity":"有效"},"message":"查询成功！","status":200}