{"code":"0","data":{"overDate":"2023-06-01","note":null,"addTime":null,"proofOrSerialCode":"2105-441900-04-01-825073","submitDate":"2021/05/27 10:32:12","fullName":"东莞市桥头镇经济发展局","updateTime":"2022/09/27 09:16:46","expiryDate":"2023/05/31 14:06:52","applyOrgan":"东莞市锐特硅胶制品有限公司","beginDate":"2021-06-01","hasStart":0,"sfjz":"0","scope":"占地面积19341.69平方米，总建筑面积为58000平方米，其中，包括厂房54700平方米、办公楼3300平方米，。主要生产：硅橡胶，硅橡胶年生产10000万吨。主要生产设备为捏合机和滤胶机，采用GB/T531技术生产产品，提高制造效率，年产量为10000万吨，","finishDate":"2021-05-31","id":"e317d9d5-73ae-11ec-9ad9-fa164ee08b71","place":"东莞市桥头镇华厦路128号","stateFlagName":"办结（通过）","projectName":"锐特硅橡胶生产建设项目","totalInvest":11260.0000,"isValidity":"有效"},"message":"查询成功！","status":200}