{"code":"0","data":{"overDate":"2023-05-01","note":null,"addTime":null,"proofOrSerialCode":"2303-441900-04-01-912834","submitDate":"2023/03/23 16:35:43","fullName":"东莞市大朗镇经济发展局","updateTime":"2023/04/03 15:18:45","expiryDate":"2025-03-24","applyOrgan":"十亿仓（东莞）科技有限公司","beginDate":"2023-03-01","hasStart":0,"sfjz":"0","scope":"在广东省东莞市大朗镇洋乌村富升路249号建筑屋顶建设55.76KWp分布式光伏发电项目，采用热镀锌支架安装光伏发电系统，拟安装410W单晶硅光伏组件，占用屋顶272平方米，预计年发电量7.5万度，产品技术及系统安装符合国家行业规范。          \n建筑面积:272 平方米 占地面积:272 平方米","finishDate":"2023-03-24","id":"1639192889453969409","place":"东莞市大朗镇洋乌村富升路249号","stateFlagName":"办结（通过）","projectName":"十亿仓(东莞)科技有限公司55.76KWp分布式光伏发电项目","totalInvest":28.0000,"isValidity":"有效"},"message":"查询成功！","status":200}