{"code":"0","data":{"overDate":"2022-03-01","note":null,"addTime":null,"proofOrSerialCode":"2112-441900-04-01-748726","submitDate":"2021/12/16 17:39:46","fullName":"东莞市麻涌镇经济发展局","updateTime":"2022/09/27 09:16:46","expiryDate":"2023/12/30 15:50:40","applyOrgan":"东莞市麻涌镇新基股份经济联合社","beginDate":"2022-01-01","hasStart":0,"sfjz":"0","scope":"东莞市麻涌镇新基村旧基坊街道升级改造工程项目：包括对旧基坊街道进行升级改造，工程主要包括路面修复平整，加铺沥青，铺设行人道，升级排水，三线管道铺设，修整沿岸，长250米，路宽8米。","finishDate":"2021-12-30","id":"e4123faf-73ae-11ec-9ad9-fa164ee08b71","place":"东莞市麻涌镇东莞市麻涌镇新基村内","stateFlagName":"办结（通过）","projectName":"东莞市麻涌镇新基村旧基坊街道升级改造工程","totalInvest":120.0000,"isValidity":"有效"},"message":"查询成功！","status":200}