{"code":"0","data":{"overDate":"2023-10-01","note":null,"addTime":null,"proofOrSerialCode":"2204-441900-04-01-382836","submitDate":"2022/04/14 18:13:29","fullName":"东莞市发展和改革局","updateTime":"2022/09/27 09:16:46","expiryDate":"2024/04/18 17:06:22","applyOrgan":"东莞市中海嘉桦房地产开发有限公司","beginDate":"2022-04-01","hasStart":0,"sfjz":"0","scope":"建筑面积7625.18平方米，占地面积38816.32平方米。新建变压器容量630KVA，充电站总功率1470KW。桩数210台。功率：7KW交流充电桩210台。充电机类型：交流充电机。满足210台电动车同时充电，新建小区配套。符合消防安全等充电设施安全运营要求的配套设施和系统。","finishDate":"2022-04-18","id":"1515980041798811649","place":"东莞市大岭山镇大沙村","stateFlagName":"办结（通过）","projectName":"东莞市大岭山镇中海松湖华庭充电桩新建项目","totalInvest":100.0000,"isValidity":"有效"},"message":"查询成功！","status":200}