{"code":"0","data":{"overDate":"2022-12-01","note":null,"addTime":null,"proofOrSerialCode":"2020-441900-29-03-086689","submitDate":"2020/09/24 10:39:55","fullName":"东莞市企石镇经济发展局","updateTime":"2022/09/27 09:16:46","expiryDate":"2022/09/24 11:55:20","applyOrgan":"东莞市企石镇莫屋股份经济联合社","beginDate":"2021-04-01","hasStart":0,"sfjz":"0","scope":"项目占地9769.66平方米，总建筑面积32034平方米。项目建设厂房及宿舍，购置生产线，企业主要从事塑胶精密组件、五金制品、电子产品、模具、医疗器械配件的产销及研发。","finishDate":"2020-09-24","id":"e22d9420-73ae-11ec-9ad9-fa164ee08b71","place":"东莞市企石镇莫屋发展路10号","stateFlagName":"办结（通过）","projectName":"东莞市盈通精密组件有限公司扩建项目","totalInvest":17200.0000,"isValidity":"有效"},"message":"查询成功！","status":200}