{"code":"0","data":{"overDate":"2022-12-01","note":null,"addTime":null,"proofOrSerialCode":"2209-441900-04-01-910699","submitDate":"2022/09/29 16:21:06","fullName":"东莞市石碣镇经济发展局","updateTime":"2023/02/17 09:52:00","expiryDate":"2024-09-30","applyOrgan":"东莞市石碣鸿叶塑料制品贸易部","beginDate":"2022-10-01","hasStart":0,"sfjz":"0","scope":"东莞石碣鸿叶塑料制品贸易部，在自有的东莞市石碣镇横滘科技中路171号办公楼上建设54.18KW分布式光伏发电项目，采用高效单晶硅420W光伏组件，占用屋顶面积约200平方米，年平均发电量约为59万度电，产品技术及安装系统符合国家相关行业标准。","finishDate":"2022-09-30","id":"1575660857596055553","place":"东莞市石碣镇石碣科技中路171号","stateFlagName":"办结（通过）","projectName":"东莞石碣鸿叶塑料制品贸易部54.18KW分布式光伏发电项目","totalInvest":34.0000,"isValidity":"有效"},"message":"查询成功！","status":200}