{"code":"0","data":{"overDate":"2025-11-01","note":null,"addTime":null,"proofOrSerialCode":"2209-441900-04-01-913271","submitDate":"2022/09/26 15:06:05","fullName":"东莞市石碣镇经济发展局","updateTime":"2022/09/28 09:42:06","expiryDate":"2024-09-26","applyOrgan":"东莞市首铸星城房地产开发有限公司","beginDate":"2022-11-01","hasStart":0,"sfjz":"0","scope":"本项目规划总用地面积为50904.52平方米，总建筑面积约为23万平方米，主要建设住宅、商业、物业管理用房、地下车库、幼儿园等。","finishDate":"2022-09-26","id":"1574323233874776066","place":"东莞市石碣镇刘屋村、横滘村","stateFlagName":"办结（通过）","projectName":"君汇府","totalInvest":300000.0000,"isValidity":"有效"},"message":"查询成功！","status":200}