{"code":"0","data":{"overDate":"2024-01-01","note":null,"addTime":null,"proofOrSerialCode":"2302-441900-04-05-625393","submitDate":"2023/02/13 09:32:37","fullName":"东莞市高埗镇经济发展局","updateTime":"2023/04/11 11:32:33","expiryDate":"2025-02-14","applyOrgan":"东莞市顺贰新能源投资有限公司","beginDate":"2023-02-01","hasStart":0,"sfjz":"0","scope":"我司东莞市顺贰新能源投资有限公司拟在自建的企业东莞市华欣五金制品有限公司的厂房楼顶上建设773.85kWp分布式光伏发电项目，拟安装550Wp光伏组件1407块，项目拟占用屋顶面积约4000平方米，项目符合光伏建设管理办法第十五条要求即“平面屋顶项目光伏组件最高点距离铺设平面的高度不得高于2.8米，具有楼梯间的居民楼项目光伏组件不得高于梯间屋面1米（最高点应不高于屋顶屋面4米），并且四周均不得围蔽形成建筑使用空间”。采用自发自用，余电上网\"的并网模式，年平均发电约85万kWp，产品技术及系统安装符合相关国家和行业标准。","finishDate":"2023-02-14","id":"1625313880559337474","place":"东莞市高埗镇卢村工业区","stateFlagName":"办结（通过）","projectName":"东莞市华欣五金制品有限公司773.85kWp分布式光伏发电项目","totalInvest":320.0000,"isValidity":"有效"},"message":"查询成功！","status":200}