{"code":"0","data":{"overDate":"2023-12-01","note":null,"addTime":null,"proofOrSerialCode":"2205-441900-04-01-998045","submitDate":"2022/05/20 08:47:01","fullName":"东莞市发展和改革局","updateTime":"2022/09/27 09:16:46","expiryDate":"2024-05-23","applyOrgan":"东莞盈盛新能源科技有限公司","beginDate":"2022-05-01","hasStart":0,"sfjz":"0","scope":"本项目建筑面积4400平方米，占地面积4400平方米，一期建设2台800kVA变压器、6台120kW直流双枪充电桩1台640kW直流充电堆（1超充+15快充），合计28个充电车位。二期建设72个车位（50台7kW交流桩）合计50个充电车位，剩余22车位用作休息室及其他配套设施。总合计100个车位。","finishDate":"2022-05-23","id":"1528541219024642050","place":"东莞市寮步镇香市路73号欧尚东莞寮步店","stateFlagName":"办结（通过）","projectName":"东莞欧尚超市有限公司充电站新建项目新建项目","totalInvest":800.0000,"isValidity":"有效"},"message":"查询成功！","status":200}