{"code":"0","data":{"overDate":"2022-12-01","note":null,"addTime":null,"proofOrSerialCode":"2207-441900-04-01-726960","submitDate":"2022/07/22 11:27:12","fullName":"东莞市长安镇经济发展局","updateTime":"2022/09/27 09:16:46","expiryDate":"2024-07-25","applyOrgan":"东莞市长安世代传承红木家具馆","beginDate":"2022-07-01","hasStart":0,"sfjz":"0","scope":"拟在4127平方米楼顶建设198KW光伏发电项目，采用自发自用模式，年发电量27.6万度，每年减碳排放18吨左右为环保作贡献，0.4kv并网，采用480块高效晶硅太阳能组件，逆变器3台，产品技术安装系统符合国家行业标准。","finishDate":"2022-07-25","id":"1551416956949753858","place":"东莞市长安镇  乌沙兴三路13号","stateFlagName":"办结（通过）","projectName":"长安乌沙春科厂198千瓦太阳能光伏发电项目","totalInvest":120.0000,"isValidity":"有效"},"message":"查询成功！","status":200}