{"code":"0","data":{"overDate":"2022-11-01","note":null,"addTime":null,"proofOrSerialCode":"2020-441900-34-03-062103","submitDate":"2020/07/21 10:42:55","fullName":"东莞市大朗镇经济发展局","updateTime":"2022/09/27 09:16:46","expiryDate":"2022/07/31 08:59:52","applyOrgan":"东莞市大朗镇宝陂股份经济联合社","beginDate":"2020-11-01","hasStart":0,"sfjz":"0","scope":"该项目占地面积7654.65平方米，建筑面积22963.95平方米，计划建设工业厂房1栋，该项目主要从事铝制品剪切生产,年产量铝制品400万件。","finishDate":"2020-07-31","id":"e1ecfe3b-73ae-11ec-9ad9-fa164ee08b71","place":"东莞市大朗镇富民二园宝陂工业区","stateFlagName":"办结（通过）","projectName":"东莞市大朗镇宝陂股份经济联合社雅励金属材料剪切生产项目","totalInvest":4650.0000,"isValidity":"有效"},"message":"查询成功！","status":200}