{"code":"0","data":{"overDate":"2023-05-01","note":null,"addTime":null,"proofOrSerialCode":"2105-441900-04-01-971749","submitDate":"2021/05/05 22:43:32","fullName":"东莞市沙田镇经济发展局","updateTime":"2022/09/27 09:16:46","expiryDate":"2023/05/07 15:56:13","applyOrgan":"增益供应链（东莞）有限公司","beginDate":"2021-05-01","hasStart":0,"sfjz":"0","scope":"项目建筑面积约19441.36平方米，占地面积约47204.60平方米。主要建筑物有冷库及配套设施等。冷库主要服务对象为储存预包装食品、散装食品、肉类、水果、蔬菜等生鲜产品和冷冻产品，以中转仓储为主，配套加工分拣配送功能，综合周转率约11%。","finishDate":"2021-05-07","id":"e2feec27-73ae-11ec-9ad9-fa164ee08b71","place":"东莞市沙田镇西大坦物流中路旁","stateFlagName":"办结（通过）","projectName":"联想增益供应链华南总部基地项目（冷链一区）2号冷库","totalInvest":13768.5700,"isValidity":"有效"},"message":"查询成功！","status":200}