{"code":"0","data":{"overDate":"2024-06-01","note":null,"addTime":null,"proofOrSerialCode":"2203-441900-04-01-342325","submitDate":"2022/03/23 15:18:03","fullName":"东莞市望牛墩镇经济发展局","updateTime":"2022/09/27 09:16:46","expiryDate":"2024/03/25 17:03:41","applyOrgan":"东莞顺裕纸业有限公司","beginDate":"2022-12-01","hasStart":0,"sfjz":"0","scope":"本项目总建筑面积31000平方米，主要建筑仓库一栋一层，用于新型包装材料的生产，采用高度智能化制造技术，拟计划引进两条国外进口的瓦楞纸板生产线、智能物流系统及智能仓库系统各一套，引进2台德国-DHS、1台荷兰-智能点数机、1台德国-全自动转运车、1台德国-全自动打包机，同时配套国内领先的产品检测设备、信息系统等国产先进设备及信息化系统。项目达产后预计年产24万吨（3.6亿平方米）新型包装材料，年产值达1200万/亩，年税收80万元/亩以上。","finishDate":"2022-03-25","id":"1507282056856522754","place":"东莞市望牛墩镇锦涡村","stateFlagName":"办结（通过）","projectName":"顺裕智能环保包装产业项目","totalInvest":30000.0000,"isValidity":"有效"},"message":"查询成功！","status":200}