{"code":"0","data":{"overDate":"2020-12-01","note":null,"addTime":null,"proofOrSerialCode":"2020-441900-48-03-054791","submitDate":"2020/06/30 11:14:20","fullName":"东莞市道滘镇经济发展局","updateTime":"2022/09/27 09:16:46","expiryDate":"2022/07/02 14:25:59","applyOrgan":"东莞市道滘镇永庆股份经济联合社","beginDate":"2020-08-01","hasStart":0,"sfjz":"0","scope":"道滘镇永庆村创建特色村庄工程项目—三丫涌永庆段南北两岸沿河景观提升工程，总投资约1500万，主要涉及：园建工程、给排水工程、电气工程、绿化工程等。","finishDate":"2020-07-02","id":"e1d934ab-73ae-11ec-9ad9-fa164ee08b71","place":"东莞市道滘镇永庆村","stateFlagName":"办结（通过）","projectName":"道滘镇永庆村创建特色村庄工程项目—三丫涌永庆段南北两岸沿河景观提升工程","totalInvest":1500.0000,"isValidity":"有效"},"message":"查询成功！","status":200}