{"code":"0","data":{"overDate":"2023-12-01","note":null,"addTime":null,"proofOrSerialCode":"2207-441900-04-01-556054","submitDate":"2022/07/28 12:12:59","fullName":"东莞市茶山镇经济发展局","updateTime":"2022/09/27 09:16:46","expiryDate":"2024-07-28","applyOrgan":"东莞市茶山镇刘黄股份经济联合社","beginDate":"2022-09-01","hasStart":0,"sfjz":"0","scope":"主要建设1栋九层的1号厂房、1栋六层的1号宿舍及1栋1层的电房，用地面积约5510.8平方米，建筑面积为15766.9平方米。项目建成后拟招引电子和五金行业相关企业。","finishDate":"2022-07-28","id":"1552551042082795521","place":"东莞市茶山镇刘黄村工业三路","stateFlagName":"办结（通过）","projectName":"茶山镇刘黄村“元差塘”1 号厂房及1号宿舍工程","totalInvest":4509.0000,"isValidity":"有效"},"message":"查询成功！","status":200}