{"code":"0","data":{"overDate":"2022-03-01","note":null,"addTime":null,"proofOrSerialCode":"2112-441900-04-01-235275","submitDate":"2021/12/28 16:00:05","fullName":"东莞市塘厦镇经济发展局","updateTime":"2022/09/27 09:16:46","expiryDate":"2023/12/30 16:42:13","applyOrgan":"东莞市海鹏实业有限公司","beginDate":"2022-01-01","hasStart":0,"sfjz":"0","scope":"在2145平方米建筑屋顶上自有资金投资新建分布式光伏电站206.08kw，组件功率为460W，数量448块，年发电量26.3万度，产品技术及系统安装符合相关国家和行业标准。","finishDate":"2021-12-30","id":"e4214b1a-73ae-11ec-9ad9-fa164ee08b71","place":"东莞市塘厦镇林村宏业北路166号","stateFlagName":"办结（通过）","projectName":"东莞市塘厦镇海鹏实业有限公司206.08kw分布式光伏新建项目","totalInvest":157.0000,"isValidity":"有效"},"message":"查询成功！","status":200}