{"code":"0","data":{"overDate":"2023-05-01","note":null,"addTime":null,"proofOrSerialCode":"2208-441900-04-01-196955","submitDate":"2022/08/24 10:39:31","fullName":"东莞市石排镇经济发展局","updateTime":"2022/09/27 09:16:46","expiryDate":"2024-08-25","applyOrgan":"东莞市石排镇埔心股份经济联合社","beginDate":"2022-10-01","hasStart":0,"sfjz":"0","scope":"项目位于石排镇埔心村沿河路，占地约2000平方米，主要对现有广场地面进行翻新重新铺设，新建党建文化设施，新建电气项目及相关绿化附属工程。","finishDate":"2022-08-25","id":"1562635881393799169","place":"东莞市石排镇埔心村沿河路248号","stateFlagName":"办结（通过）","projectName":"埔心村沿河路人居环境整治工程","totalInvest":110.0000,"isValidity":"有效"},"message":"查询成功！","status":200}