{"code":"0","data":{"overDate":"2023-06-01","note":null,"addTime":null,"proofOrSerialCode":"2303-441900-04-01-959071","submitDate":"2023/03/06 10:34:37","fullName":"东莞市大岭山镇经济发展局","updateTime":"2023/03/07 11:00:03","expiryDate":"2025-03-07","applyOrgan":"东莞市大岭山镇大塘朗股份经济联合社","beginDate":"2023-04-01","hasStart":0,"sfjz":"0","scope":"本工程为投资金额约300万元的景观升级改造工程，所含内容包括但不限于：园建工程、道路工程、安装工程、绿化工程等。","finishDate":"2023-03-07","id":"1632939126917447681","place":"东莞市大岭山镇大塘朗村","stateFlagName":"办结（通过）","projectName":"大塘朗村景观升级改造工程","totalInvest":300.0000,"isValidity":"有效"},"message":"查询成功！","status":200}