{"code":"0","data":{"overDate":"2021-04-01","note":null,"addTime":null,"proofOrSerialCode":"2102-441900-04-01-584879","submitDate":"2021/01/18 13:05:53","fullName":"东莞市厚街镇经济发展局","updateTime":"2022/09/27 09:16:46","expiryDate":"2023/02/10 11:58:18","applyOrgan":"东莞市茂叶物业管理有限公司","beginDate":"2021-02-01","hasStart":0,"sfjz":"0","scope":"在租赁的650平方米宿舍楼屋顶上自有资金投资新建分布式光伏电站122.1kw，组件为隆基乐叶光伏组件，功率为370w每块，数量为330块，年发电量15.6万度，产品技术及系统安装符合相关国家和行业标准","finishDate":"2021-02-10","id":"e2a0e7f9-73ae-11ec-9ad9-fa164ee08b71","place":"东莞市厚街镇沙塘康乐东街一号","stateFlagName":"办结（通过）","projectName":"东莞市茂叶物业管理有限公司宿舍楼122.1kw分布式光伏新建项目","totalInvest":47.0000,"isValidity":"有效"},"message":"查询成功！","status":200}