{"code":"0","data":{"overDate":"2024-06-01","note":null,"addTime":null,"proofOrSerialCode":"2110-441900-04-01-266642","submitDate":"2021/10/28 16:18:00","fullName":"东莞市松山湖产业发展局","updateTime":"2022/11/08 14:33:08","expiryDate":"2023-10-28","applyOrgan":"东莞市创研尚实业投资有限公司","beginDate":"2022-05-01","hasStart":0,"sfjz":"0","scope":"项目占地面积35557.75平方米，建筑面积104778.76平方米，主要建筑物为研发办公楼，产品名称：科研设计。","finishDate":"2021-10-28","id":"e3c829aa-73ae-11ec-9ad9-fa164ee08b71","place":"东莞市松山湖松山湖北部工业城","stateFlagName":"办结（通过）","projectName":"创研尚设计研发中心（二期）","totalInvest":25272.7700,"isValidity":"有效"},"message":"查询成功！","status":200}