{"code":"0","data":{"overDate":"2017-12-01","note":null,"addTime":null,"proofOrSerialCode":"2017-441900-52-03-009628","submitDate":"2017/08/29 11:52:02","fullName":"东莞市发展和改革局","updateTime":"2022/09/27 09:16:46","expiryDate":"2019/11/01 11:38:56","applyOrgan":"东莞市嘉禾贸易有限公司","beginDate":"2017-11-01","hasStart":1,"sfjz":"0","scope":"东莞市嘉禾贸易公司在企业自有工业厂房上投资建设227.92KW光伏分布式发电项目，采用280W单晶硅太阳能组件814片，占地面积为4410平方米，建筑面积为9200平方米；电站建成后平均年发电量为33万度电，产品技术及系统安装符合国家和行业标准。","finishDate":"2017-10-31","id":"dec6b75f-73ae-11ec-9ad9-fa164ee08b71","place":"东莞市大岭山镇颜屋村莞长路颜屋段150号","stateFlagName":"办结（通过）","projectName":"东莞市大岭山镇嘉禾贸易227.92KW分布式光伏发电项目","totalInvest":87.0000,"isValidity":"有效"},"message":"查询成功！","status":200}