{"code":"0","data":{"overDate":"2023-05-01","note":null,"addTime":null,"proofOrSerialCode":"2209-441900-04-05-285421","submitDate":"2022/09/28 11:07:33","fullName":"东莞市高埗镇经济发展局","updateTime":"2023/01/31 14:51:04","expiryDate":"2024-09-29","applyOrgan":"东莞市祥钦新能源技术有限公司","beginDate":"2022-10-01","hasStart":0,"sfjz":"0","scope":"东莞市祥钦新能源技术有限公司拟在5370平方米的房顶建设799.7KW光伏发电项目，拟安装1454块550Wp单晶太阳能组件，平均年发电量79万度，产品系统及技术安装符合相关行业和国家标准。","finishDate":"2022-09-29","id":"1575334557526265858","place":"东莞市高埗镇冼沙三塘路成铭胶粘剂有限公司厂房A~B,仓库屋顶","stateFlagName":"办结（通过）","projectName":"东莞市成铭胶粘剂有限公司799.7kw分布式光伏发电项目","totalInvest":300.0000,"isValidity":"有效"},"message":"查询成功！","status":200}