{"code":"0","data":{"overDate":"2022-06-01","note":null,"addTime":null,"proofOrSerialCode":"2109-441900-04-01-728872","submitDate":"2021/08/31 17:33:12","fullName":"东莞市高埗镇经济发展局","updateTime":"2022/09/27 09:16:46","expiryDate":"2023/09/02 16:18:18","applyOrgan":"东莞市高埗镇新联股份经济联合社","beginDate":"2021-10-01","hasStart":0,"sfjz":"0","scope":"本工程为高埗镇新联村雨污分流工程181、182地块企石村雨污分流工程。主要涉及内容为新联企石村雨污分流，拟新建雨污分流管道3857米，新建雨水立管3381米。","finishDate":"2021-09-02","id":"e38c006e-73ae-11ec-9ad9-fa164ee08b71","place":"东莞市高埗镇广东省东莞市高埗镇中心西路93附近","stateFlagName":"办结（通过）","projectName":"高埗镇新联村雨污分流工程181、182地块企石村","totalInvest":270.0000,"isValidity":"有效"},"message":"查询成功！","status":200}