{"code":"0","data":{"overDate":"2025-05-01","note":null,"addTime":null,"proofOrSerialCode":"2020-441900-83-03-088979","submitDate":"2020/09/29 17:32:01","fullName":"东莞市黄江镇经济发展局","updateTime":"2023/03/16 09:42:26","expiryDate":"2023-10-13","applyOrgan":"东莞市升旺实业投资有限公司","beginDate":"2022-09-01","hasStart":0,"sfjz":"0","scope":"项目以拆除重建为主。主要内容：幼儿园用地1830.78平方米，建筑面积为1990平方米，容积率为1。","finishDate":"2020-10-13","id":"e2329dd9-73ae-11ec-9ad9-fa164ee08b71","place":"东莞市黄江镇板湖村","stateFlagName":"办结（通过）","projectName":"黄江镇上群花园幼儿园项目","totalInvest":738.0000,"isValidity":"有效"},"message":"查询成功！","status":200}