{"code":"0","data":{"overDate":"2019-12-01","note":null,"addTime":null,"proofOrSerialCode":"2018-441900-41-03-811968","submitDate":"2018/07/12 15:05:34","fullName":"东莞市清溪镇经济发展局","updateTime":"2022/09/27 09:16:46","expiryDate":"2099-01-01","applyOrgan":"明门（中国）幼童用品有限公司","beginDate":"2018-07-01","hasStart":1,"sfjz":"0","scope":"占地面积：145433.72㎡；建筑面积:440000㎡；延续新建：宿舍楼占地面积约：2000㎡；建筑面积约16000㎡；厂房七占地面积约：7000㎡；建筑面积约：60000㎡；公司主要生产：生产婴儿手推车及其配件、婴儿围栏及其配件、学步车、餐椅、婴儿摇椅、座椅、棉被、背袋、各种玩具及其零配件等.","finishDate":"2018-07-19","id":"dfb7ff2b-73ae-11ec-9ad9-fa164ee08b71","place":"东莞市清溪镇银河工业区","stateFlagName":"办结（通过）","projectName":"明门（中国）幼童用品有限公司厂区","totalInvest":8000.0000,"isValidity":"有效"},"message":"查询成功！","status":200}