{"code":"0","data":{"overDate":"2023-01-01","note":null,"addTime":null,"proofOrSerialCode":"2212-441900-04-01-229347","submitDate":"2022/12/09 10:56:39","fullName":"东莞市大岭山镇经济发展局","updateTime":"2022/12/09 16:11:57","expiryDate":"2024-12-09","applyOrgan":"东莞市优刻科技有限公司","beginDate":"2022-11-01","hasStart":0,"sfjz":"0","scope":"本公司为电子烟出口生产加工企业，项目建有电子烟组装生产线一条，设计生产能力：一次性电子烟800万支/年，烟具50万支/年，烟弹300万支/年，建设代加工生产组装车间、仓库、办公区及相关配套设施，建筑面积共计2000平方米。   ","finishDate":"2022-12-09","id":"1601127485070639105","place":"东莞市大岭山镇祥锋街80号5栋402室","stateFlagName":"办结（通过）","projectName":"东莞市优刻科技有限公司电子烟产品生产项目","totalInvest":200.0000,"isValidity":"有效"},"message":"查询成功！","status":200}