{"code":"0","data":{"overDate":"2019-05-01","note":null,"addTime":null,"proofOrSerialCode":"2019-441900-44-03-009846","submitDate":"2019/03/05 15:26:43","fullName":"东莞市发展和改革局","updateTime":"2022/09/27 09:16:46","expiryDate":"2021/03/14 14:48:03","applyOrgan":"广东轩辕新能源科技有限公司","beginDate":"2019-03-01","hasStart":1,"sfjz":"0","scope":"东莞常平半岛酒店出大门右侧，计划安装新国标120KW直流双枪充电桩4台，建筑面积4平方米，充电时临时占用8个车位，占地面积80平方米，安装调试对接公共系统后，对社会大众纯电动车辆提供充电服务","finishDate":"2019-03-14","id":"e0675037-73ae-11ec-9ad9-fa164ee08b71","place":"东莞市常平镇东莞市常平镇北环路半岛酒店大门出口右侧","stateFlagName":"办结（通过）","projectName":"轩辕新能源东莞常平半岛酒店充电站","totalInvest":100.0000,"isValidity":"有效"},"message":"查询成功！","status":200}