{"code":"0","data":{"overDate":"2020-12-01","note":null,"addTime":null,"proofOrSerialCode":"2020-441900-78-03-042778","submitDate":"2020/05/28 10:43:30","fullName":"东莞市麻涌镇经济发展局","updateTime":"2022/09/27 09:16:46","expiryDate":"2022/06/01 11:35:49","applyOrgan":"东莞市麻涌镇麻一股份经济联合社","beginDate":"2020-06-01","hasStart":0,"sfjz":"0","scope":"东莞市麻涌镇特色精品示范村工程-麻一村对村原有基础设施进行升级改造，改造面积约15000平方米，包括市政道路升级改造工程、园建工程、牌坊工程、房建工程、照明工程等。","finishDate":"2020-06-01","id":"e1ba341b-73ae-11ec-9ad9-fa164ee08b71","place":"东莞市麻涌镇麻一村内","stateFlagName":"办结（通过）","projectName":"东莞市麻涌镇特色精品示范村工程-麻一村","totalInvest":2000.0000,"isValidity":"有效"},"message":"查询成功！","status":200}