{"code":"0","data":{"overDate":"2022-06-01","note":null,"addTime":null,"proofOrSerialCode":"2111-441900-04-01-286036","submitDate":"2021/11/12 17:43:50","fullName":"东莞市大岭山镇经济发展局","updateTime":"2022/09/27 09:16:46","expiryDate":"2023/11/18 15:01:07","applyOrgan":"东莞市大岭山镇百花洞股份经济联合社","beginDate":"2021-12-01","hasStart":0,"sfjz":"0","scope":"百花洞村创建特色精品村项目工程，包括：家具厂门前停车场、木制品厂门前停车场、荔枝公园、老年活动中心环境提升、农民公寓环境提升、旧村人居环境提升、一河两岸景观打造、红耕农田项目等。","finishDate":"2021-11-18","id":"e3e59bf8-73ae-11ec-9ad9-fa164ee08b71","place":"东莞市大岭山镇百花洞村","stateFlagName":"办结（通过）","projectName":"百花洞村创建特色精品村项目","totalInvest":1700.0000,"isValidity":"有效"},"message":"查询成功！","status":200}