{"code":"0","data":{"overDate":"2022-01-01","note":null,"addTime":null,"proofOrSerialCode":"2109-441900-04-01-259941","submitDate":"2021/08/27 16:22:17","fullName":"东莞市黄江镇经济发展局","updateTime":"2022/09/27 09:16:46","expiryDate":"2023/09/10 10:11:18","applyOrgan":"东莞市黄江镇龙见田股份经济联合社","beginDate":"2021-09-01","hasStart":0,"sfjz":"0","scope":"龙见田乡村振兴文艺运动广场公园工程，施工内容包括：文艺运动广场、文艺运动公园占地约1770平方米、东江纵队马山战斗阵地遗址登山步道及景观平台、原室外篮球场升级改造占地约1700平方米、村史馆建筑面积约150平方米，总投资约1400万元。","finishDate":"2021-09-10","id":"e3880c15-73ae-11ec-9ad9-fa164ee08b71","place":"东莞市黄江镇龙见田村","stateFlagName":"办结（通过）","projectName":"龙见田乡村振兴文艺运动广场公园工程","totalInvest":1400.0000,"isValidity":"有效"},"message":"查询成功！","status":200}