{"code":"0","data":{"overDate":"2024-04-01","note":null,"addTime":null,"proofOrSerialCode":"2110-441900-04-01-838271","submitDate":"2021/10/19 17:43:29","fullName":"东莞市塘厦镇经济发展局","updateTime":"2022/09/27 09:16:46","expiryDate":"2023/10/22 09:09:25","applyOrgan":"东莞市奥海科技股份有限公司","beginDate":"2021-10-01","hasStart":0,"sfjz":"0","scope":"项目占地面积34012.01平方米，建筑面积131719.77平方米。建有一栋厂房、一栋生产厂房、一栋宿舍楼。项目引入先进的快充及大功率电源生产线，包括全自动印刷机、SPI、NXT-III贴片机、回流焊、AOI、插件机、自动老化＋成品测试设备等，主要产品及设计生产能力为快充及大功率电源产品4845万只。","finishDate":"2021-10-22","id":"e3c3ea73-73ae-11ec-9ad9-fa164ee08b71","place":"东莞市塘厦镇沙新路27号","stateFlagName":"办结（通过）","projectName":"快充及大功率电源智能化生产建设项目","totalInvest":140777.9500,"isValidity":"有效"},"message":"查询成功！","status":200}