{"code":"0","data":{"overDate":"2024-03-01","note":null,"addTime":null,"proofOrSerialCode":"2111-441900-04-01-668684","submitDate":"2021/11/15 16:57:21","fullName":"东莞市塘厦镇经济发展局","updateTime":"2022/10/20 16:41:07","expiryDate":"2023-11-19","applyOrgan":"东莞市伟顺实业投资有限公司","beginDate":"2022-03-01","hasStart":0,"sfjz":"0","scope":"新建1栋厂房、1栋宿舍；占地面积：8030.98平方米，总建筑面积：31402.50平方米。产品名称：金属制品，年产金属制品150万件。","finishDate":"2021-11-19","id":"e3d42707-73ae-11ec-9ad9-fa164ee08b71","place":"东莞市塘厦镇平山社区","stateFlagName":"办结（通过）","projectName":"东莞市伟顺实业投资有限公司金属制品生产项目","totalInvest":6622.0000,"isValidity":"有效"},"message":"查询成功！","status":200}