{"code":"0","data":{"overDate":"2026-06-01","note":null,"addTime":null,"proofOrSerialCode":"2110-441900-04-01-213392","submitDate":"2021/10/29 11:33:44","fullName":"东莞滨海湾新区管理委员会（东莞港管理委员会）","updateTime":"2022/09/27 09:16:46","expiryDate":"2023/10/29 16:22:20","applyOrgan":"东莞市滨海湾新区控股有限公司","beginDate":"2022-06-01","hasStart":0,"sfjz":"0","scope":"项目规划选址于滨海湾新区交椅湾板块，占地面积约179亩，建筑面积约23.89万平方米，项目总投资额约14.81亿元。项目定位为现代高端产业园区，重点聚焦人工智能、电子信息，打造为新区乃至于粤港澳大湾区重要的现代产业集聚与创新资源集聚平台,建成后将形成企业公馆区、产业研发区、协同创新区。","finishDate":"2021-10-29","id":"e3d146d9-73ae-11ec-9ad9-fa164ee08b71","place":"东莞市滨海湾新区东莞市滨海湾","stateFlagName":"办结（通过）","projectName":"滨海湾·科技创新基地","totalInvest":148100.0000,"isValidity":"有效"},"message":"查询成功！","status":200}