{"code":"0","data":{"overDate":"2022-11-01","note":null,"addTime":null,"proofOrSerialCode":"2209-441900-04-01-416218","submitDate":"2022/09/22 17:37:56","fullName":"东莞市大朗镇经济发展局","updateTime":"2022/09/27 09:16:46","expiryDate":"2024-09-23","applyOrgan":"东莞市涛汶能源有限公司","beginDate":"2022-09-01","hasStart":0,"sfjz":"0","scope":"东莞市涛汶能源有限公司在工业厂房屋顶上建设226.84千瓦分布式光伏发电项目，安装265W多晶硅太阳能板856块，占用厂房面积约2814.74平方米，平均年发电量为29万KWh。产品技术及系统安装符合相关国家和行业标准。","finishDate":"2022-09-23","id":"1573219365619240962","place":"东莞市大朗镇新马莲村云莲七街29号","stateFlagName":"办结（通过）","projectName":"东莞市涛汶能源有限公司226.84千瓦分布式光伏发电项目","totalInvest":192.0000,"isValidity":"有效"},"message":"查询成功！","status":200}