{"code":"0","data":{"overDate":"2021-12-01","note":null,"addTime":null,"proofOrSerialCode":"2110-441900-04-01-552710","submitDate":"2021/10/20 10:00:52","fullName":"东莞市清溪镇经济发展局","updateTime":"2022/09/27 09:16:46","expiryDate":"2023/10/21 17:06:22","applyOrgan":"广东嘀嗒酷显柔性显示科技有限公司","beginDate":"2021-10-01","hasStart":0,"sfjz":"0","scope":"项目规划用地面积是3000平方米，总建筑10360平方米，主要装修建设柔性显示工艺研发车间","finishDate":"2021-10-21","id":"e3c4a613-73ae-11ec-9ad9-fa164ee08b71","place":"东莞市清溪镇莲中西街10号201室","stateFlagName":"办结（通过）","projectName":"嘀嗒柔性显示工艺自动化投产建设项目","totalInvest":118.0000,"isValidity":"有效"},"message":"查询成功！","status":200}