{"code":"0","data":{"overDate":"2022-04-01","note":null,"addTime":null,"proofOrSerialCode":"2202-441900-04-01-546436","submitDate":"2022/02/09 13:17:28","fullName":"东莞市清溪镇经济发展局","updateTime":"2022/09/27 09:16:46","expiryDate":"2024/02/18 09:55:25","applyOrgan":"东莞市清溪镇铁场股份经济联合社","beginDate":"2022-03-01","hasStart":0,"sfjz":"0","scope":"本工程新敷设0.4kV电缆共2137米，新架设导线共656米，新建低压配电箱基础7座，箱体彩绘33.6平方米，新建电缆行车埋管井共33座，新建行车排管共1346米；拆除水泥杆30根、低压架空线共3558米、铁塔基础3基。总投资金额约600万元。","finishDate":"2022-02-18","id":"a311f1cc-50b1-4231-a76e-2f8589d32a25","place":"东莞市清溪镇铁场村","stateFlagName":"办结（通过）","projectName":"清溪镇铁场村三线下地电力迁改工程","totalInvest":600.0000,"isValidity":"有效"},"message":"查询成功！","status":200}